Workbook
Name RiskMatrixRef: 'set up'!$C$14

Sheet Data Rights Notice

Sheet 0100 Hull System
O2: Risk Ranking | AB2: Updated Risk Ranking | AN2: 2nd Updated Risk Ranking
B4: 0100 Hull Structure FMECA Table | P4: Severity Class | T4: Risk Class | AC4: Severity Class | AG4: Risk Class | AO4: Severity Class | AS4: Risk Class
B5: Risk ID | C5: Item Description | D5: Function | E5: Tech. Class | F5: Novel Aspects | G5: Failure Mode | H5: Failure Effects (Local, WEC, System) | I5: Failure Cause(s) | J5: Initial Mode of Operation | K5: Risk Reduction Design | L5: Preventative Detection | M5: Post Failure Detection | N5: Post Failure Repair Strategy (automated, manual) | O5: Occurrence | P5: Human Safety | Q5: Environment | R5: Operation | S5: Assets | T5: Human Safety | U5: Environment | V5: Operation | W5: Assets | X5: Recommended Actions | Y5: DNV GL comment | Z5: Responsible Party | AA5: Actions Taken | AB5: Occurrence | AC5: Human Safety | AD5: Environment | AE5: Operation | AF5: Assets | AG5: Human Safety | AH5: Environment | AI5: Operation | AJ5: Assets | AK5: 2nd Recommended Actions | AL5: Responsible Party (2nd) | AM5: Actions Taken (2nd) | AN5: Occurrence | AO5: Human Safety | AP5: Environment | AQ5: Operation | AR5: Assets | AS5: Human Safety | AT5: Environment | AU5: Operation | AV5: Assets | AW5: Status (open or closed) | AX5: Notes
B6: 0100-1 | C6: Hull | D6: Wave activated body Provision of watertight compartment Structural connectivity & load transfer Ballast containment | E6: 2 | F6: Loading in wave environment, with large motions | G6: Severe structural failure | H6: Severe structural failure WEC is no longer functioning | I6: Extreme wave event loading (Overloading) | J6: Normal | K6: none | L6: none | M6: 1) Surveillance 2) SCADA 3) etc | N6: Dry dock repair if possible, if not loss of projects | O6: 3 | P6: 4 | Q6: 7 | R6: 9 | S6: 9 | T6: =IF(AND(ISNUMBER(P6),ISNUMBER($O6)),OFFSET(RiskMatrixRef,-$O6+1,P6-1),"") -> Low | U6: =IF(AND(ISNUMBER(Q6),ISNUMBER($O6)),OFFSET(RiskMatrixRef,-$O6+1,Q6-1),"") -> Low | V6: =IF(AND(ISNUMBER(R6),ISNUMBER($O6)),OFFSET(RiskMatrixRef,-$O6+1,R6-1),"") -> Med | W6: =IF(AND(ISNUMBER(S6),ISNUMBER($O6)),OFFSET(RiskMatrixRef,-$O6+1,S6-1),"") -> Med | X6: 1) Load derivation methodology to take into account the uncertainties in the loading due to site characterisation measurements and hydrodynamic modelling. 2) Uncertainty of loading estimates to be reduced by comparison of hydrodynamic behavior in simulation versus tank testing. 3) Design load cases to be defined considering all phases (e.g. operating w/ fault, installation, etc.), and to include investigation of localized loading from e.g. slamming. 4) Derivation of localized loading to be developed, and validated via instrumentation of prototype at-sea deployment. | Y6: Suggested text for recommended action: The uncertainty about loading needs to be reduced by tank testing and development (and comparison) of simulation of hydrodynamic behaviour considering PTO and controls as well as implementation of structural calculations to derive design stresses. Derivation of localised loading such as slamming or other aspects associated with tolerances and local distribution of loading as well as events associated with faults has to be developed and validated. The design load cases have to be defined considering all phases such as Operating, Operating with fault, Survival, Survival with fault, Damaged, Transport and Installation, etc. | AG6: =IF(AND(ISNUMBER(AC6),ISNUMBER($AB6)),OFFSET(RiskMatrixRef,-$AB6+1,AC6-1),"") | AH6: =IF(AND(ISNUMBER(AD6),ISNUMBER($AB6)),OFFSET(RiskMatrixRef,-$AB6+1,AD6-1),"") | AI6: =IF(AND(ISNUMBER(AE6),ISNUMBER($AB6)),OFFSET(RiskMatrixRef,-$AB6+1,AE6-1),"") | AJ6: =IF(AND(ISNUMBER(AF6),ISNUMBER($AB6)),OFFSET(RiskMatrixRef,-$AB6+1,AF6-1),"") | AS6: =IF(AND(ISNUMBER(AO6),ISNUMBER($AN6)),OFFSET(RiskMatrixRef,-$AN6+1,AO6-1),"") | AT6: =IF(AND(ISNUMBER(AP6),ISNUMBER($AN6)),OFFSET(RiskMatrixRef,-$AN6+1,AP6-1),"") | AU6: =IF(AND(ISNUMBER(AQ6),ISNUMBER($AN6)),OFFSET(RiskMatrixRef,-$AN6+1,AQ6-1),"") | AV6: =IF(AND(ISNUMBER(AR6),ISNUMBER($AN6)),OFFSET(RiskMatrixRef,-$AN6+1,AR6-1),"")
B7: 0100-2 | C7: Hull | D7: Wave activated body Provision of watertight compartment Structural connectivity & load transfer Ballast containment | E7: 2 | F7: Loading in wave environment, with large motions | G7: Severe structural failure | H7: Severe structural failure WEC is no longer functioning | I7: Fatigue and other degradation mechanisms | J7: Normal | K7: none | L7: none | M7: 1) Surveillance 2) SCADA 3) etc | N7: Dry dock repair if possible, if not loss of projects | O7: 7 | P7: 4 | Q7: 7 | R7: 9 | S7: 9 | T7: =IF(AND(ISNUMBER(P7),ISNUMBER($O7)),OFFSET(RiskMatrixRef,-$O7+1,P7-1),"") -> Low | U7: =IF(AND(ISNUMBER(Q7),ISNUMBER($O7)),OFFSET(RiskMatrixRef,-$O7+1,Q7-1),"") -> Med | V7: =IF(AND(ISNUMBER(R7),ISNUMBER($O7)),OFFSET(RiskMatrixRef,-$O7+1,R7-1),"") -> High | W7: =IF(AND(ISNUMBER(S7),ISNUMBER($O7)),OFFSET(RiskMatrixRef,-$O7+1,S7-1),"") -> High | X7: 1) Load derivation methodology to take into account the uncertainties in the loading due to site characterisation measurements and hydrodynamic modelling. 2) Uncertainty of loading estimates to be reduced by comparison of hydrodynamic behavior in simulation versus tank testing. 3) Design load cases to be defined considering all phases (e.g. operating w/ fault, installation, etc.), and to include investigation of localized loading from e.g. slamming. 4) Derivation of localized loading to be developed, and validated via instrumentation of prototype at-sea deployment. 5) Design fatigue factors (DFF) shall be applied to reduce probability of fatigue failure. 6) Design to incorporate cathodic protection and coating as appropriate (under subsystem 0645 Marinization and Corrosion, External) 7) Establish inspection plan | Y7: Probability class increased to be compatible with FLS design. Suggested text for recommended action: Increase DFF, implementation of cathodic protection and coating, inspection plan. The uncertainty about loading needs to be reduced by tank testing and development (and comparison) of simulation of hydrodynamic behaviour considering PTO and controls as well as implementation of structural calculations to derive design stresses. Derivation of localised loading such as slamming or other aspects associated with tolerances and local distribution of loading as well as events associated with faults has to be developed and validated. The design load cases have to be defined considering all phases such as Operating, Operating with fault, Survival, Survival with fault, Damaged, Transport and Installation, etc. | AG7: =IF(AND(ISNUMBER(AC7),ISNUMBER($AB7)),OFFSET(RiskMatrixRef,-$AB7+1,AC7-1),"") | AH7: =IF(AND(ISNUMBER(AD7),ISNUMBER($AB7)),OFFSET(RiskMatrixRef,-$AB7+1,AD7-1),"") | AI7: =IF(AND(ISNUMBER(AE7),ISNUMBER($AB7)),OFFSET(RiskMatrixRef,-$AB7+1,AE7-1),"") | AJ7: =IF(AND(ISNUMBER(AF7),ISNUMBER($AB7)),OFFSET(RiskMatrixRef,-$AB7+1,AF7-1),"") | AS7: =IF(AND(ISNUMBER(AO7),ISNUMBER($AN7)),OFFSET(RiskMatrixRef,-$AN7+1,AO7-1),"") | AT7: =IF(AND(ISNUMBER(AP7),ISNUMBER($AN7)),OFFSET(RiskMatrixRef,-$AN7+1,AP7-1),"") | AU7: =IF(AND(ISNUMBER(AQ7),ISNUMBER($AN7)),OFFSET(RiskMatrixRef,-$AN7+1,AQ7-1),"") | AV7: =IF(AND(ISNUMBER(AR7),ISNUMBER($AN7)),OFFSET(RiskMatrixRef,-$AN7+1,AR7-1),"")
B8: 0111-1 0121-1 | C8: Forward float Aft float | D8: Wave activated body Provision of watertight compartment | E8: 2 | F8: Loading in wave environment, with large motions | G8: Crack/hole in float (leading to water drainage) | H8: 1) Sub-optimal performance 2) change in buoyancy 3) only a portion of water may drain (see note) | I8: Leak in FRP (e.g. manufacturing flaw, assembly) *not boat strikes* | J8: Normal | K8: 1) vacuum test all water tight compartments 2) All ballast water below waterline 3) Foam fill open voids 4) V&V for manufacturing and assembly | M8: 1) visual inspection of draft line on floats 2) average angle of the floats seen by encoders | N8: Dry dock for FRP repair | O8: 4 | P8: 1 | Q8: 1 | R8: 7 | S8: 7 | T8: =IF(AND(ISNUMBER(P8),ISNUMBER($O8)),OFFSET(RiskMatrixRef,-$O8+1,P8-1),"") -> Low | U8: =IF(AND(ISNUMBER(Q8),ISNUMBER($O8)),OFFSET(RiskMatrixRef,-$O8+1,Q8-1),"") -> Low | V8: =IF(AND(ISNUMBER(R8),ISNUMBER($O8)),OFFSET(RiskMatrixRef,-$O8+1,R8-1),"") -> Low | W8: =IF(AND(ISNUMBER(S8),ISNUMBER($O8)),OFFSET(RiskMatrixRef,-$O8+1,S8-1),"") -> Low | X8: 1) V&V procedures to be defined and followed, which shall mitigate risk of defective component up to commissioning. | Y8: See comment on failure effects and causes | AG8: =IF(AND(ISNUMBER(AC8),ISNUMBER($AB8)),OFFSET(RiskMatrixRef,-$AB8+1,AC8-1),"") | AH8: =IF(AND(ISNUMBER(AD8),ISNUMBER($AB8)),OFFSET(RiskMatrixRef,-$AB8+1,AD8-1),"") | AI8: =IF(AND(ISNUMBER(AE8),ISNUMBER($AB8)),OFFSET(RiskMatrixRef,-$AB8+1,AE8-1),"") | AJ8: =IF(AND(ISNUMBER(AF8),ISNUMBER($AB8)),OFFSET(RiskMatrixRef,-$AB8+1,AF8-1),"") | AS8: =IF(AND(ISNUMBER(AO8),ISNUMBER($AN8)),OFFSET(RiskMatrixRef,-$AN8+1,AO8-1),"") | AT8: =IF(AND(ISNUMBER(AP8),ISNUMBER($AN8)),OFFSET(RiskMatrixRef,-$AN8+1,AP8-1),"") | AU8: =IF(AND(ISNUMBER(AQ8),ISNUMBER($AN8)),OFFSET(RiskMatrixRef,-$AN8+1,AQ8-1),"") | AV8: =IF(AND(ISNUMBER(AR8),ISNUMBER($AN8)),OFFSET(RiskMatrixRef,-$AN8+1,AR8-1),"") | AX8: only a small portion of water may drain, as ballast water will be below still water line
B9: 0111-2 0121-2 | C9: Forward float Aft float | D9: Wave activated body Provision of watertight compartment | E9: 2 | F9: Loading in wave environment, with large motions | G9: Crack/hole in float (leading to water drainage) | H9: 1) Sub-optimal performance 2) change in buoyancy 3) only a portion of water may drain (see note) | I9: Leak in FRP - fatigue crack due to uncertainties in loading | J9: Normal | K9: 1) All ballast water below waterline 2) Foam fill open voids | M9: 1) visual inspection of draft line on floats 2) average angle of the floats seen by encoders | N9: Dry dock for FRP repair | O9: 7 | P9: 1 | Q9: 1 | R9: 7 | S9: 7 | T9: =IF(AND(ISNUMBER(P9),ISNUMBER($O9)),OFFSET(RiskMatrixRef,-$O9+1,P9-1),"") -> Low | U9: =IF(AND(ISNUMBER(Q9),ISNUMBER($O9)),OFFSET(RiskMatrixRef,-$O9+1,Q9-1),"") -> Low | V9: =IF(AND(ISNUMBER(R9),ISNUMBER($O9)),OFFSET(RiskMatrixRef,-$O9+1,R9-1),"") -> Med | W9: =IF(AND(ISNUMBER(S9),ISNUMBER($O9)),OFFSET(RiskMatrixRef,-$O9+1,S9-1),"") -> Med | X9: 1) Load derivation methodology to take into account the uncertainties in the loading due to site characterisation measurements and hydrodynamic modelling. 2) Uncertainty of loading estimates to be reduced by comparison of hydrodynamic behavior in simulation versus tank testing. 3) Design load cases to be defined considering all phases (e.g. operating w/ fault, installation, etc.), and to include investigation of localized loading from e.g. slamming. 4) Derivation of localized loading to be developed, and validated via instrumentation of prototype at-sea deployment. 5) Design fatigue factors (DFF) shall be applied to reduce probability of fatigue failure. 6) Establish inspection plan | Y9: Action the same as "Fatigue and other degradation mechanisms" for hull. | AG9: =IF(AND(ISNUMBER(AC9),ISNUMBER($AB9)),OFFSET(RiskMatrixRef,-$AB9+1,AC9-1),"") | AH9: =IF(AND(ISNUMBER(AD9),ISNUMBER($AB9)),OFFSET(RiskMatrixRef,-$AB9+1,AD9-1),"") | AI9: =IF(AND(ISNUMBER(AE9),ISNUMBER($AB9)),OFFSET(RiskMatrixRef,-$AB9+1,AE9-1),"") | AJ9: =IF(AND(ISNUMBER(AF9),ISNUMBER($AB9)),OFFSET(RiskMatrixRef,-$AB9+1,AF9-1),"") | AS9: =IF(AND(ISNUMBER(AO9),ISNUMBER($AN9)),OFFSET(RiskMatrixRef,-$AN9+1,AO9-1),"") | AT9: =IF(AND(ISNUMBER(AP9),ISNUMBER($AN9)),OFFSET(RiskMatrixRef,-$AN9+1,AP9-1),"") | AU9: =IF(AND(ISNUMBER(AQ9),ISNUMBER($AN9)),OFFSET(RiskMatrixRef,-$AN9+1,AQ9-1),"") | AV9: =IF(AND(ISNUMBER(AR9),ISNUMBER($AN9)),OFFSET(RiskMatrixRef,-$AN9+1,AR9-1),"") | AX9: only a small portion of water may drain, as ballast water will be below still water line
B10: 0111-3 0121-3 | C10: Forward float Aft float | D10: Wave activated body Provision of watertight compartment | E10: 2 | F10: Loading in wave environment, with large motions | G10: Locked / reduced motion | H10: 1) Float becomes locked or reduced motion w.r.t. nacelle | I10: Debris caught between float and nacelle (or spar) | J10: Normal | K10: smooth edges | L10: surveillance camera checks/visual inspection | M10: 1) PTO not moving or reduced motion 2) Surveillance cameras | N10: Remove debris In situ or dry dock repair of FRP if warranted | O10: 6 | P10: 1 | Q10: 1 | R10: 7 | S10: 7 | T10: =IF(AND(ISNUMBER(P10),ISNUMBER($O10)),OFFSET(RiskMatrixRef,-$O10+1,P10-1),"") -> Low | U10: =IF(AND(ISNUMBER(Q10),ISNUMBER($O10)),OFFSET(RiskMatrixRef,-$O10+1,Q10-1),"") -> Low | V10: =IF(AND(ISNUMBER(R10),ISNUMBER($O10)),OFFSET(RiskMatrixRef,-$O10+1,R10-1),"") -> Med | W10: =IF(AND(ISNUMBER(S10),ISNUMBER($O10)),OFFSET(RiskMatrixRef,-$O10+1,S10-1),"") -> Med | X10: 1) Probability of occurrence of debris to be verified for site conditions 2) Type and dimensions of problem debris to be specified for the site | Y10: The probability of occurrence is to be verified for the site conditions and it is also necessary to define the type of debris and dimension that would be a problem. | AG10: =IF(AND(ISNUMBER(AC10),ISNUMBER($AB10)),OFFSET(RiskMatrixRef,-$AB10+1,AC10-1),"") | AH10: =IF(AND(ISNUMBER(AD10),ISNUMBER($AB10)),OFFSET(RiskMatrixRef,-$AB10+1,AD10-1),"") | AI10: =IF(AND(ISNUMBER(AE10),ISNUMBER($AB10)),OFFSET(RiskMatrixRef,-$AB10+1,AE10-1),"") | AJ10: =IF(AND(ISNUMBER(AF10),ISNUMBER($AB10)),OFFSET(RiskMatrixRef,-$AB10+1,AF10-1),"") | AS10: =IF(AND(ISNUMBER(AO10),ISNUMBER($AN10)),OFFSET(RiskMatrixRef,-$AN10+1,AO10-1),"") | AT10: =IF(AND(ISNUMBER(AP10),ISNUMBER($AN10)),OFFSET(RiskMatrixRef,-$AN10+1,AP10-1),"") | AU10: =IF(AND(ISNUMBER(AQ10),ISNUMBER($AN10)),OFFSET(RiskMatrixRef,-$AN10+1,AQ10-1),"") | AV10: =IF(AND(ISNUMBER(AR10),ISNUMBER($AN10)),OFFSET(RiskMatrixRef,-$AN10+1,AR10-1),"")
B11: 0111-4 0121-4 | C11: Forward float Aft float | D11: Wave activated body Provision of watertight compartment | E11: 2 | F11: Loading in wave environment, with large motions | G11: Locked / reduced motion | H11: 1) Float becomes locked or reduced motion w.r.t. nacelle | I11: Large mammal caught betweeen float and nacelle (or spar) | J11: Normal | K11: smooth edges | M11: 1) PTO not moving or reduced motion 2) Surveillance cameras | N11: Remove mammal | O11: 3 | P11: 1 | Q11: 5 | R11: 5 | S11: 5 | T11: =IF(AND(ISNUMBER(P11),ISNUMBER($O11)),OFFSET(RiskMatrixRef,-$O11+1,P11-1),"") -> Low | U11: =IF(AND(ISNUMBER(Q11),ISNUMBER($O11)),OFFSET(RiskMatrixRef,-$O11+1,Q11-1),"") -> Low | V11: =IF(AND(ISNUMBER(R11),ISNUMBER($O11)),OFFSET(RiskMatrixRef,-$O11+1,R11-1),"") -> Low | W11: =IF(AND(ISNUMBER(S11),ISNUMBER($O11)),OFFSET(RiskMatrixRef,-$O11+1,S11-1),"") -> Low | X11: 1) Probability of occurrence to be evaluated by the assessment of presence and behavior of mammals on site. | Y11: Probability of occurrence to be evaluated by the assessment of presence of mammals on site. | AG11: =IF(AND(ISNUMBER(AC11),ISNUMBER($AB11)),OFFSET(RiskMatrixRef,-$AB11+1,AC11-1),"") | AH11: =IF(AND(ISNUMBER(AD11),ISNUMBER($AB11)),OFFSET(RiskMatrixRef,-$AB11+1,AD11-1),"") | AI11: =IF(AND(ISNUMBER(AE11),ISNUMBER($AB11)),OFFSET(RiskMatrixRef,-$AB11+1,AE11-1),"") | AJ11: =IF(AND(ISNUMBER(AF11),ISNUMBER($AB11)),OFFSET(RiskMatrixRef,-$AB11+1,AF11-1),"") | AS11: =IF(AND(ISNUMBER(AO11),ISNUMBER($AN11)),OFFSET(RiskMatrixRef,-$AN11+1,AO11-1),"") | AT11: =IF(AND(ISNUMBER(AP11),ISNUMBER($AN11)),OFFSET(RiskMatrixRef,-$AN11+1,AP11-1),"") | AU11: =IF(AND(ISNUMBER(AQ11),ISNUMBER($AN11)),OFFSET(RiskMatrixRef,-$AN11+1,AQ11-1),"") | AV11: =IF(AND(ISNUMBER(AR11),ISNUMBER($AN11)),OFFSET(RiskMatrixRef,-$AN11+1,AR11-1),"")
B12: 0111-5 0121-5 | C12: Forward float Aft float | D12: Wave activated body Provision of watertight compartment | E12: 2 | F12: Loading in wave environment, with large motions | G12: Mammal take | H12: 1) mammal take | I12: Large mammal caught betweeen float and nacelle (or spar) | J12: Normal | K12: smooth edges | M12: 1) Surveillance cameras | N12: Remove mammal | O12: 6 | P12: 1 | Q12: 5 | R12: 5 | S12: 5 | T12: =IF(AND(ISNUMBER(P12),ISNUMBER($O12)),OFFSET(RiskMatrixRef,-$O12+1,P12-1),"") -> Low | U12: =IF(AND(ISNUMBER(Q12),ISNUMBER($O12)),OFFSET(RiskMatrixRef,-$O12+1,Q12-1),"") -> Low | V12: =IF(AND(ISNUMBER(R12),ISNUMBER($O12)),OFFSET(RiskMatrixRef,-$O12+1,R12-1),"") -> Low | W12: =IF(AND(ISNUMBER(S12),ISNUMBER($O12)),OFFSET(RiskMatrixRef,-$O12+1,S12-1),"") -> Low | X12: 1) Probability of occurrence to be evaluated by the assessment of presence and behavior of mammals on site. | Y12: Probability of occurrence to be evaluated by the assessment of presence of mammals on site. | AG12: =IF(AND(ISNUMBER(AC12),ISNUMBER($AB12)),OFFSET(RiskMatrixRef,-$AB12+1,AC12-1),"") | AH12: =IF(AND(ISNUMBER(AD12),ISNUMBER($AB12)),OFFSET(RiskMatrixRef,-$AB12+1,AD12-1),"") | AI12: =IF(AND(ISNUMBER(AE12),ISNUMBER($AB12)),OFFSET(RiskMatrixRef,-$AB12+1,AE12-1),"") | AJ12: =IF(AND(ISNUMBER(AF12),ISNUMBER($AB12)),OFFSET(RiskMatrixRef,-$AB12+1,AF12-1),"") | AS12: =IF(AND(ISNUMBER(AO12),ISNUMBER($AN12)),OFFSET(RiskMatrixRef,-$AN12+1,AO12-1),"") | AT12: =IF(AND(ISNUMBER(AP12),ISNUMBER($AN12)),OFFSET(RiskMatrixRef,-$AN12+1,AP12-1),"") | AU12: =IF(AND(ISNUMBER(AQ12),ISNUMBER($AN12)),OFFSET(RiskMatrixRef,-$AN12+1,AQ12-1),"") | AV12: =IF(AND(ISNUMBER(AR12),ISNUMBER($AN12)),OFFSET(RiskMatrixRef,-$AN12+1,AR12-1),"")
B13: 0111-6 0121-6 | C13: Forward float Aft float | D13: Wave activated body Provision of watertight compartment | E13: 2 | F13: Loading in wave environment, with large motions | G13: Service human trapped | H13: 1) Human trapped 2) Potential fatality | I13: service worker falls inbetween fwd float and nacelle | J13: Normal | K13: none | M13: 1) Surveillance cameras | O13: 3 | P13: 10 | Q13: 1 | R13: 1 | S13: 1 | T13: =IF(AND(ISNUMBER(P13),ISNUMBER($O13)),OFFSET(RiskMatrixRef,-$O13+1,P13-1),"") -> Med | U13: =IF(AND(ISNUMBER(Q13),ISNUMBER($O13)),OFFSET(RiskMatrixRef,-$O13+1,Q13-1),"") -> Low | V13: =IF(AND(ISNUMBER(R13),ISNUMBER($O13)),OFFSET(RiskMatrixRef,-$O13+1,R13-1),"") -> Low | W13: =IF(AND(ISNUMBER(S13),ISNUMBER($O13)),OFFSET(RiskMatrixRef,-$O13+1,S13-1),"") -> Low | X13: 1) Design guard netting to significantly reduce the liklihood of entrapment and/or death 2) The probability of occurrence is to be verified against procedures for access and how the integrity of the net is maintained. | Y13: The probability of occurrence is to be verified against procedures for access and how the integrity of the net is maintained. | AG13: =IF(AND(ISNUMBER(AC13),ISNUMBER($AB13)),OFFSET(RiskMatrixRef,-$AB13+1,AC13-1),"") | AH13: =IF(AND(ISNUMBER(AD13),ISNUMBER($AB13)),OFFSET(RiskMatrixRef,-$AB13+1,AD13-1),"") | AI13: =IF(AND(ISNUMBER(AE13),ISNUMBER($AB13)),OFFSET(RiskMatrixRef,-$AB13+1,AE13-1),"") | AJ13: =IF(AND(ISNUMBER(AF13),ISNUMBER($AB13)),OFFSET(RiskMatrixRef,-$AB13+1,AF13-1),"") | AS13: =IF(AND(ISNUMBER(AO13),ISNUMBER($AN13)),OFFSET(RiskMatrixRef,-$AN13+1,AO13-1),"") | AT13: =IF(AND(ISNUMBER(AP13),ISNUMBER($AN13)),OFFSET(RiskMatrixRef,-$AN13+1,AP13-1),"") | AU13: =IF(AND(ISNUMBER(AQ13),ISNUMBER($AN13)),OFFSET(RiskMatrixRef,-$AN13+1,AQ13-1),"") | AV13: =IF(AND(ISNUMBER(AR13),ISNUMBER($AN13)),OFFSET(RiskMatrixRef,-$AN13+1,AR13-1),"")
B14: 0111-7 0121-7 | C14: Forward float Aft float | D14: Wave activated body Provision of watertight compartment | E14: 2 | F14: Loading in wave environment, with large motions | G14: Public human trapped | H14: 1) Human trapped 2) Potential fatality | I14: unauthorized personel falls inbetween fwd float and nacelle | J14: Normal | K14: none | M14: 1) Surveillance cameras | O14: 3 | P14: 10 | Q14: 1 | R14: 1 | S14: 1 | T14: =IF(AND(ISNUMBER(P14),ISNUMBER($O14)),OFFSET(RiskMatrixRef,-$O14+1,P14-1),"") -> Med | U14: =IF(AND(ISNUMBER(Q14),ISNUMBER($O14)),OFFSET(RiskMatrixRef,-$O14+1,Q14-1),"") -> Low | V14: =IF(AND(ISNUMBER(R14),ISNUMBER($O14)),OFFSET(RiskMatrixRef,-$O14+1,R14-1),"") -> Low | W14: =IF(AND(ISNUMBER(S14),ISNUMBER($O14)),OFFSET(RiskMatrixRef,-$O14+1,S14-1),"") -> Low | X14: 1) Design guard netting to significantly reduce the liklihood of entrapment and/or death 2) Design of the net to demonstrate that its integrity is maintained throughout its life time. | Y14: Suggest text for recommended action: Design of the net to demonstrate that its integrity is maintained throughout its life time. | AG14: =IF(AND(ISNUMBER(AC14),ISNUMBER($AB14)),OFFSET(RiskMatrixRef,-$AB14+1,AC14-1),"") | AH14: =IF(AND(ISNUMBER(AD14),ISNUMBER($AB14)),OFFSET(RiskMatrixRef,-$AB14+1,AD14-1),"") | AI14: =IF(AND(ISNUMBER(AE14),ISNUMBER($AB14)),OFFSET(RiskMatrixRef,-$AB14+1,AE14-1),"") | AJ14: =IF(AND(ISNUMBER(AF14),ISNUMBER($AB14)),OFFSET(RiskMatrixRef,-$AB14+1,AF14-1),"") | AS14: =IF(AND(ISNUMBER(AO14),ISNUMBER($AN14)),OFFSET(RiskMatrixRef,-$AN14+1,AO14-1),"") | AT14: =IF(AND(ISNUMBER(AP14),ISNUMBER($AN14)),OFFSET(RiskMatrixRef,-$AN14+1,AP14-1),"") | AU14: =IF(AND(ISNUMBER(AQ14),ISNUMBER($AN14)),OFFSET(RiskMatrixRef,-$AN14+1,AQ14-1),"") | AV14: =IF(AND(ISNUMBER(AR14),ISNUMBER($AN14)),OFFSET(RiskMatrixRef,-$AN14+1,AR14-1),"")
B15: 0111-8 0121-8 | C15: Forward float Aft float | D15: Wave activated body Provision of watertight compartment | E15: 2 | F15: Loading in wave environment, with large motions | G15: Hole in float (leading to water drainage) | H15: 1) Loss of performance 2) Loss of known physical parameters (weight of each component) 3) change in buoyancy | I15: Debris caught between float and another body, leading to wear that creates a hole that changes buoyancy | J15: Normal | K15: smooth edges | L15: surveillance camera checks/visual inspection | M15: 1) visual inspection of draft line on floats 2) average angle of the floats seen by encoders | N15: Dry dock for FRP repair | O15: 5 | P15: 1 | Q15: 1 | R15: 6 | S15: 7 | T15: =IF(AND(ISNUMBER(P15),ISNUMBER($O15)),OFFSET(RiskMatrixRef,-$O15+1,P15-1),"") -> Low | U15: =IF(AND(ISNUMBER(Q15),ISNUMBER($O15)),OFFSET(RiskMatrixRef,-$O15+1,Q15-1),"") -> Low | V15: =IF(AND(ISNUMBER(R15),ISNUMBER($O15)),OFFSET(RiskMatrixRef,-$O15+1,R15-1),"") -> Low | W15: =IF(AND(ISNUMBER(S15),ISNUMBER($O15)),OFFSET(RiskMatrixRef,-$O15+1,S15-1),"") -> Med | X15: 1) Probability of occurrence of debris to be verified for site conditions 2) Type and dimensions of problem debris to be specified for the site 3) Additional thickness to be considered in areas that wear could occur. 4) Identify the magnitude of wear and time to inspect / repair. 5) Design to demonstrate wear rate due to debris is within the acceptance criteria for the long term structural integrity of the hull | Y15: Suggest text for recommended action: Additional thickness to be considered in areas that wear could occur. Identify the magnitude of wear and time to inspect / repair. If the wear is created by the debris, the type of debris that could be a problem and their existence on site to be verified. Design to demonstrate wear rate due to debris is within the acceptance criteria for the long term structural integrity of the hull | AG15: =IF(AND(ISNUMBER(AC15),ISNUMBER($AB15)),OFFSET(RiskMatrixRef,-$AB15+1,AC15-1),"") | AH15: =IF(AND(ISNUMBER(AD15),ISNUMBER($AB15)),OFFSET(RiskMatrixRef,-$AB15+1,AD15-1),"") | AI15: =IF(AND(ISNUMBER(AE15),ISNUMBER($AB15)),OFFSET(RiskMatrixRef,-$AB15+1,AE15-1),"") | AJ15: =IF(AND(ISNUMBER(AF15),ISNUMBER($AB15)),OFFSET(RiskMatrixRef,-$AB15+1,AF15-1),"") | AS15: =IF(AND(ISNUMBER(AO15),ISNUMBER($AN15)),OFFSET(RiskMatrixRef,-$AN15+1,AO15-1),"") | AT15: =IF(AND(ISNUMBER(AP15),ISNUMBER($AN15)),OFFSET(RiskMatrixRef,-$AN15+1,AP15-1),"") | AU15: =IF(AND(ISNUMBER(AQ15),ISNUMBER($AN15)),OFFSET(RiskMatrixRef,-$AN15+1,AQ15-1),"") | AV15: =IF(AND(ISNUMBER(AR15),ISNUMBER($AN15)),OFFSET(RiskMatrixRef,-$AN15+1,AR15-1),"")
B16: 0111-9 0121-9 | C16: Forward float Aft float | D16: Wave activated body Provision of watertight compartment | E16: 2 | F16: Loading in wave environment, with large motions | G16: Hole in float (leading to water drainage) | H16: 1) Loss of performance 2) Loss of known physical parameters (weight of each component) 3) change in buoyancy | I16: Float arms flexed more than expected. Wear creates a hole that changes buoyancy | J16: Normal | K16: none | L16: surveillance camera checks/visual inspection | M16: 1) visual inspection of draft line on floats 2) average angle of the floats seen by encoders | N16: Dry dock for FRP repair | O16: 5 | P16: 1 | Q16: 1 | R16: 6 | S16: 7 | T16: =IF(AND(ISNUMBER(P16),ISNUMBER($O16)),OFFSET(RiskMatrixRef,-$O16+1,P16-1),"") -> Low | U16: =IF(AND(ISNUMBER(Q16),ISNUMBER($O16)),OFFSET(RiskMatrixRef,-$O16+1,Q16-1),"") -> Low | V16: =IF(AND(ISNUMBER(R16),ISNUMBER($O16)),OFFSET(RiskMatrixRef,-$O16+1,R16-1),"") -> Low | W16: =IF(AND(ISNUMBER(S16),ISNUMBER($O16)),OFFSET(RiskMatrixRef,-$O16+1,S16-1),"") -> Med | X16: 1) Additional thickness to be considered in areas that wear could occur. 2) Identify the expected magnitude of wear and time to inspect / repair. 3) Specify inspection plan to be implemented after deployment. 4) Design to consider addition safety margin on space between components (where rubbing and wear is possible) to allow for uncertainty of loading and structural stiffness. | Y16: Suggest text for recommended action: Additional thickness to be considered in areas that wear could occur. Identify the magnitude of wear and time to inspect / repair. Inspection plan to be implemented after deployment. Design to consider addition safety margin on air gap to allow for uncertainty on loading and structural stiffness. | AG16: =IF(AND(ISNUMBER(AC16),ISNUMBER($AB16)),OFFSET(RiskMatrixRef,-$AB16+1,AC16-1),"") | AH16: =IF(AND(ISNUMBER(AD16),ISNUMBER($AB16)),OFFSET(RiskMatrixRef,-$AB16+1,AD16-1),"") | AI16: =IF(AND(ISNUMBER(AE16),ISNUMBER($AB16)),OFFSET(RiskMatrixRef,-$AB16+1,AE16-1),"") | AJ16: =IF(AND(ISNUMBER(AF16),ISNUMBER($AB16)),OFFSET(RiskMatrixRef,-$AB16+1,AF16-1),"") | AS16: =IF(AND(ISNUMBER(AO16),ISNUMBER($AN16)),OFFSET(RiskMatrixRef,-$AN16+1,AO16-1),"") | AT16: =IF(AND(ISNUMBER(AP16),ISNUMBER($AN16)),OFFSET(RiskMatrixRef,-$AN16+1,AP16-1),"") | AU16: =IF(AND(ISNUMBER(AQ16),ISNUMBER($AN16)),OFFSET(RiskMatrixRef,-$AN16+1,AQ16-1),"") | AV16: =IF(AND(ISNUMBER(AR16),ISNUMBER($AN16)),OFFSET(RiskMatrixRef,-$AN16+1,AR16-1),"")
B17: 0111-10 0121-10 | C17: Forward float Aft float | D17: Wave activated body Provision of watertight compartment | E17: 2 | F17: Loading in wave environment, with large motions | G17: Hole in float (leading to water drainage) | H17: 1) Sub-optimal performance 2) Increased generator speed (>20RPM) during strike event 3) change in buoyancy | I17: Non-service Boat Strike | J17: Normal | K17: 1) Lights, radar reflectors (e.g. visibility) | L17: none | M17: 1) visual inspection of draft line on floats 2) average angle of the floats seen by encoders | N17: In situ FRP repair if possible (hole above waterline and known location) Worst case: Dry dock inspection and repair of WEC. | O17: 8 | P17: 4 | Q17: 1 | R17: 6 | S17: 7 | T17: =IF(AND(ISNUMBER(P17),ISNUMBER($O17)),OFFSET(RiskMatrixRef,-$O17+1,P17-1),"") -> Med | U17: =IF(AND(ISNUMBER(Q17),ISNUMBER($O17)),OFFSET(RiskMatrixRef,-$O17+1,Q17-1),"") -> Low | V17: =IF(AND(ISNUMBER(R17),ISNUMBER($O17)),OFFSET(RiskMatrixRef,-$O17+1,R17-1),"") -> Med | W17: =IF(AND(ISNUMBER(S17),ISNUMBER($O17)),OFFSET(RiskMatrixRef,-$O17+1,S17-1),"") -> Med | X17: 1) In-situ FRP repair procedure to be developed. The repair is to be qualified to the conditions of implementation (moving parts, deformation within the area of repair and splash of seawater). The durability of repair will depend if it is supposed to be permanent, temporary to allow to reach the next maintenance period or only to allow for recovery. 2) For damage below the water line, assessment of consequence to be made and design strategy to be considered to reduce probability of damage and also to improve retrieval operation. 3) establish exclusion zone at deployed area 4) The probability of occurrence to be verified considering conditions at the site and vessels in the area | Y17: Suggest text for recommended action: In-situ FRP repair procedure to be developed. The repair is to be qualified to the conditions of implementation (moving parts, deformation within the area of repair and splash of seawater. The durability of repair will depend if it is supposed to be permanent, temporary to allow to reach the next maintenance period or only to allow for recovery. for damage below the water line, assessment of consequence to be made and design strategy to be considered to reduce probability of damage and also to improve retrieval operation. | AG17: =IF(AND(ISNUMBER(AC17),ISNUMBER($AB17)),OFFSET(RiskMatrixRef,-$AB17+1,AC17-1),"") | AH17: =IF(AND(ISNUMBER(AD17),ISNUMBER($AB17)),OFFSET(RiskMatrixRef,-$AB17+1,AD17-1),"") | AI17: =IF(AND(ISNUMBER(AE17),ISNUMBER($AB17)),OFFSET(RiskMatrixRef,-$AB17+1,AE17-1),"") | AJ17: =IF(AND(ISNUMBER(AF17),ISNUMBER($AB17)),OFFSET(RiskMatrixRef,-$AB17+1,AF17-1),"") | AS17: =IF(AND(ISNUMBER(AO17),ISNUMBER($AN17)),OFFSET(RiskMatrixRef,-$AN17+1,AO17-1),"") | AT17: =IF(AND(ISNUMBER(AP17),ISNUMBER($AN17)),OFFSET(RiskMatrixRef,-$AN17+1,AP17-1),"") | AU17: =IF(AND(ISNUMBER(AQ17),ISNUMBER($AN17)),OFFSET(RiskMatrixRef,-$AN17+1,AQ17-1),"") | AV17: =IF(AND(ISNUMBER(AR17),ISNUMBER($AN17)),OFFSET(RiskMatrixRef,-$AN17+1,AR17-1),"")
B18: 0111-11 0121-11 | C18: Forward float Aft float | D18: Wave activated body Provision of watertight compartment | E18: 2 | F18: Loading in wave environment, with large motions | G18: fore/aft float breaks off | H18: 1) Wave loading of float is no longer transferred to rotor 2) Loss of power production 3) Float on Beach/Float out to sea | I18: One arm breaks off and causes higher stress on other arm so both break and float is free | J18: Normal | K18: none | L18: 1) Surveillance 2) Visual Detection 3) Dry dock before second arm breaks | M18: 1) Average angle of the floats seen by encoders 2) Surveillance | N18: 1) Recover float 2) drydock reatachment if possible | O18: 4 | P18: 4 | Q18: 5 | R18: 9 | S18: 8 | T18: =IF(AND(ISNUMBER(P18),ISNUMBER($O18)),OFFSET(RiskMatrixRef,-$O18+1,P18-1),"") -> Low | U18: =IF(AND(ISNUMBER(Q18),ISNUMBER($O18)),OFFSET(RiskMatrixRef,-$O18+1,Q18-1),"") -> Low | V18: =IF(AND(ISNUMBER(R18),ISNUMBER($O18)),OFFSET(RiskMatrixRef,-$O18+1,R18-1),"") -> Med | W18: =IF(AND(ISNUMBER(S18),ISNUMBER($O18)),OFFSET(RiskMatrixRef,-$O18+1,S18-1),"") -> Med | X18: 1) Load derivation methodology to take into account the uncertainties in the loading due to site characterisation measurements and hydrodynamic modelling. 2) Uncertainty of loading estimates to be reduced by comparison of hydrodynamic behavior in simulation versus tank testing. 3) Design load cases to be defined considering all phases (e.g. operating w/ fault, installation, etc.), and to include investigation of localized loading from e.g. slamming. 4) Derivation of localized loading to be developed, and validated via instrumentation of prototype at-sea deployment. 5) Design to consider increasing safety factors to high safety class. | Y18: Suggest text for recommended action: Increasing the safety factors to high safety class. Uncertainties on loads and structural response to be addressed as defined above (see "Extreme wave event loading" for hull.) | AG18: =IF(AND(ISNUMBER(AC18),ISNUMBER($AB18)),OFFSET(RiskMatrixRef,-$AB18+1,AC18-1),"") | AH18: =IF(AND(ISNUMBER(AD18),ISNUMBER($AB18)),OFFSET(RiskMatrixRef,-$AB18+1,AD18-1),"") | AI18: =IF(AND(ISNUMBER(AE18),ISNUMBER($AB18)),OFFSET(RiskMatrixRef,-$AB18+1,AE18-1),"") | AJ18: =IF(AND(ISNUMBER(AF18),ISNUMBER($AB18)),OFFSET(RiskMatrixRef,-$AB18+1,AF18-1),"") | AS18: =IF(AND(ISNUMBER(AO18),ISNUMBER($AN18)),OFFSET(RiskMatrixRef,-$AN18+1,AO18-1),"") | AT18: =IF(AND(ISNUMBER(AP18),ISNUMBER($AN18)),OFFSET(RiskMatrixRef,-$AN18+1,AP18-1),"") | AU18: =IF(AND(ISNUMBER(AQ18),ISNUMBER($AN18)),OFFSET(RiskMatrixRef,-$AN18+1,AQ18-1),"") | AV18: =IF(AND(ISNUMBER(AR18),ISNUMBER($AN18)),OFFSET(RiskMatrixRef,-$AN18+1,AR18-1),"")
B19: 0112-1 0122-1 | C19: Fwd float drive arm Aft float drive arm | D19: Drive starboard/port generator rotor Constrain float to relative pitch about nacelle | E19: 2 | F19: Loading in wave environment, with large motions | G19: Drive arm broken | H19: 1) Wave loading of float is no longer transferred to rotor 2) Loss of power production 3) Addtl loading on idler arm | I19: Fatigue of float arm due to uncertainties in loading | J19: Normal | K19: none | L19: none | M19: 1) PTO not moving 2) Surveillance cameras | N19: Dry dock reattachment of float arm to WEC | O19: 7 | P19: 1 | Q19: 1 | R19: 6 | S19: 7 | T19: =IF(AND(ISNUMBER(P19),ISNUMBER($O19)),OFFSET(RiskMatrixRef,-$O19+1,P19-1),"") -> Low | U19: =IF(AND(ISNUMBER(Q19),ISNUMBER($O19)),OFFSET(RiskMatrixRef,-$O19+1,Q19-1),"") -> Low | V19: =IF(AND(ISNUMBER(R19),ISNUMBER($O19)),OFFSET(RiskMatrixRef,-$O19+1,R19-1),"") -> Med | W19: =IF(AND(ISNUMBER(S19),ISNUMBER($O19)),OFFSET(RiskMatrixRef,-$O19+1,S19-1),"") -> Med | X19: 1) Load derivation methodology to take into account the uncertainties in the loading due to site characterisation measurements and hydrodynamic modelling. 2) Uncertainty of loading estimates to be reduced by comparison of hydrodynamic behavior in simulation versus tank testing. 3) Design load cases to be defined considering all phases (e.g. operating w/ fault, installation, etc.), and to include investigation of localized loading from e.g. slamming. 4) Derivation of localized loading to be developed, and validated via instrumentation of prototype at-sea deployment. 5) Design fatigue factors (DFF) shall be applied to reduce probability of fatigue failure. 6) Establish inspection plan | Y19: Action the same as "Fatigue and other degradation mechanisms" for hull. | AG19: =IF(AND(ISNUMBER(AC19),ISNUMBER($AB19)),OFFSET(RiskMatrixRef,-$AB19+1,AC19-1),"") | AH19: =IF(AND(ISNUMBER(AD19),ISNUMBER($AB19)),OFFSET(RiskMatrixRef,-$AB19+1,AD19-1),"") | AI19: =IF(AND(ISNUMBER(AE19),ISNUMBER($AB19)),OFFSET(RiskMatrixRef,-$AB19+1,AE19-1),"") | AJ19: =IF(AND(ISNUMBER(AF19),ISNUMBER($AB19)),OFFSET(RiskMatrixRef,-$AB19+1,AF19-1),"") | AS19: =IF(AND(ISNUMBER(AO19),ISNUMBER($AN19)),OFFSET(RiskMatrixRef,-$AN19+1,AO19-1),"") | AT19: =IF(AND(ISNUMBER(AP19),ISNUMBER($AN19)),OFFSET(RiskMatrixRef,-$AN19+1,AP19-1),"") | AU19: =IF(AND(ISNUMBER(AQ19),ISNUMBER($AN19)),OFFSET(RiskMatrixRef,-$AN19+1,AQ19-1),"") | AV19: =IF(AND(ISNUMBER(AR19),ISNUMBER($AN19)),OFFSET(RiskMatrixRef,-$AN19+1,AR19-1),"")
B20: 0112-2 0122-2 | C20: Fwd float drive arm Aft float drive arm | D20: Drive starboard/port generator rotor Constrain float to relative pitch about nacelle | E20: 2 | F20: Loading in wave environment, with large motions | G20: Drive arm broken | H20: 1) Wave loading of float is no longer transferred to rotor 2) Loss of power production 3) Addtl loading on idler arm | I20: Wearing of float arm, due to deflection | J20: Normal | K20: none | L20: Visual inspection, and repair if needed | M20: 1) PTO not moving 2) Surveillance cameras | N20: Dry dock reattachment of float arm to WEC | O20: 7 | P20: 1 | Q20: 1 | R20: 6 | S20: 7 | T20: =IF(AND(ISNUMBER(P20),ISNUMBER($O20)),OFFSET(RiskMatrixRef,-$O20+1,P20-1),"") -> Low | U20: =IF(AND(ISNUMBER(Q20),ISNUMBER($O20)),OFFSET(RiskMatrixRef,-$O20+1,Q20-1),"") -> Low | V20: =IF(AND(ISNUMBER(R20),ISNUMBER($O20)),OFFSET(RiskMatrixRef,-$O20+1,R20-1),"") -> Med | W20: =IF(AND(ISNUMBER(S20),ISNUMBER($O20)),OFFSET(RiskMatrixRef,-$O20+1,S20-1),"") -> Med | X20: 1) Additional thickness to be considered in areas that wear could occur. 2) Identify the expected magnitude of wear and time to inspect / repair. 3) Specify inspection plan to be implemented after deployment. 4) Design to consider additional safety margin on space between components (where rubbing and wear is possible) to allow for uncertainty of loading and structural stiffness. | Y20: Suggest text for recommended action: Additional thickness to be considered in areas that wear could occur. Identify the magnitude of wear and time to inspect / repair. Inspection plan to be implemented after deployment. Design to consider addition safety margin on air gap to allow for uncertainty on loading and structural stiffness. | AG20: =IF(AND(ISNUMBER(AC20),ISNUMBER($AB20)),OFFSET(RiskMatrixRef,-$AB20+1,AC20-1),"") | AH20: =IF(AND(ISNUMBER(AD20),ISNUMBER($AB20)),OFFSET(RiskMatrixRef,-$AB20+1,AD20-1),"") | AI20: =IF(AND(ISNUMBER(AE20),ISNUMBER($AB20)),OFFSET(RiskMatrixRef,-$AB20+1,AE20-1),"") | AJ20: =IF(AND(ISNUMBER(AF20),ISNUMBER($AB20)),OFFSET(RiskMatrixRef,-$AB20+1,AF20-1),"") | AS20: =IF(AND(ISNUMBER(AO20),ISNUMBER($AN20)),OFFSET(RiskMatrixRef,-$AN20+1,AO20-1),"") | AT20: =IF(AND(ISNUMBER(AP20),ISNUMBER($AN20)),OFFSET(RiskMatrixRef,-$AN20+1,AP20-1),"") | AU20: =IF(AND(ISNUMBER(AQ20),ISNUMBER($AN20)),OFFSET(RiskMatrixRef,-$AN20+1,AQ20-1),"") | AV20: =IF(AND(ISNUMBER(AR20),ISNUMBER($AN20)),OFFSET(RiskMatrixRef,-$AN20+1,AR20-1),"")
B21: 0112-3 0122-3 | C21: Fwd float drive arm Aft float drive arm | D21: Drive starboard/port generator rotor Constrain float to relative pitch about nacelle | E21: 2 | F21: Loading in wave environment, with large motions | G21: Drive arm broken | H21: 1) Wave loading of float is no longer transferred to rotor 2) Loss of power production 3) Addtl loading on idler arm | I21: Non-service boat strike | J21: Normal | K21: 1) Lights, radar reflectors (e.g. visibility) | L21: none | M21: 1) PTO not moving 2) Surveillance cameras | N21: Dry dock reattachment of float arm to WEC | O21: 4 | P21: 3 | Q21: 1 | R21: 6 | S21: 7 | T21: =IF(AND(ISNUMBER(P21),ISNUMBER($O21)),OFFSET(RiskMatrixRef,-$O21+1,P21-1),"") -> Low | U21: =IF(AND(ISNUMBER(Q21),ISNUMBER($O21)),OFFSET(RiskMatrixRef,-$O21+1,Q21-1),"") -> Low | V21: =IF(AND(ISNUMBER(R21),ISNUMBER($O21)),OFFSET(RiskMatrixRef,-$O21+1,R21-1),"") -> Low | W21: =IF(AND(ISNUMBER(S21),ISNUMBER($O21)),OFFSET(RiskMatrixRef,-$O21+1,S21-1),"") -> Low | X21: 1) establish exclusion zone at deployed area 2) The probability of occurrence to be verified considering conditions at the site and vessels in the area | Y21: The probability of occurrence to be verified considering conditions at the site and vessels in the area. | AG21: =IF(AND(ISNUMBER(AC21),ISNUMBER($AB21)),OFFSET(RiskMatrixRef,-$AB21+1,AC21-1),"") | AH21: =IF(AND(ISNUMBER(AD21),ISNUMBER($AB21)),OFFSET(RiskMatrixRef,-$AB21+1,AD21-1),"") | AI21: =IF(AND(ISNUMBER(AE21),ISNUMBER($AB21)),OFFSET(RiskMatrixRef,-$AB21+1,AE21-1),"") | AJ21: =IF(AND(ISNUMBER(AF21),ISNUMBER($AB21)),OFFSET(RiskMatrixRef,-$AB21+1,AF21-1),"") | AS21: =IF(AND(ISNUMBER(AO21),ISNUMBER($AN21)),OFFSET(RiskMatrixRef,-$AN21+1,AO21-1),"") | AT21: =IF(AND(ISNUMBER(AP21),ISNUMBER($AN21)),OFFSET(RiskMatrixRef,-$AN21+1,AP21-1),"") | AU21: =IF(AND(ISNUMBER(AQ21),ISNUMBER($AN21)),OFFSET(RiskMatrixRef,-$AN21+1,AQ21-1),"") | AV21: =IF(AND(ISNUMBER(AR21),ISNUMBER($AN21)),OFFSET(RiskMatrixRef,-$AN21+1,AR21-1),"")
B22: 0113-1 0123-1 | C22: Fwd float idler arm Aft float idler arm | D22: Constrain float to relative pitch about nacelle | E22: 2 | F22: Loading in wave environment, with large motions | G22: Idler arm broken | H22: 1) Wave loading of float is no longer transferred nacelle tube on idler side 2) Addtl loading on drive arm | I22: Fatigue of float arm due to uncertainties in loading | J22: Normal | K22: none | M22: 1) Surveillance cameras | N22: Dry dock reattachment of float arm to WEC | O22: 7 | P22: 1 | Q22: 1 | R22: 6 | S22: 7 | T22: =IF(AND(ISNUMBER(P22),ISNUMBER($O22)),OFFSET(RiskMatrixRef,-$O22+1,P22-1),"") -> Low | U22: =IF(AND(ISNUMBER(Q22),ISNUMBER($O22)),OFFSET(RiskMatrixRef,-$O22+1,Q22-1),"") -> Low | V22: =IF(AND(ISNUMBER(R22),ISNUMBER($O22)),OFFSET(RiskMatrixRef,-$O22+1,R22-1),"") -> Med | W22: =IF(AND(ISNUMBER(S22),ISNUMBER($O22)),OFFSET(RiskMatrixRef,-$O22+1,S22-1),"") -> Med | X22: 1) Load derivation methodology to take into account the uncertainties in the loading due to site characterisation measurements and hydrodynamic modelling. 2) Uncertainty of loading estimates to be reduced by comparison of hydrodynamic behavior in simulation versus tank testing. 3) Design load cases to be defined considering all phases (e.g. operating w/ fault, installation, etc.), and to include investigation of localized loading from e.g. slamming. 4) Derivation of localized loading to be developed, and validated via instrumentation of prototype at-sea deployment. 5) Design fatigue factors (DFF) shall be applied to reduce probability of fatigue failure. 6) Establish inspection plan | Y22: Suggest text for recommended action: Increasing the safety factors to high safety class. Uncertainties on loads and structural response to be addressed as defined above (see "Fatigue and other degradation mechanisms" for hull.) | AG22: =IF(AND(ISNUMBER(AC22),ISNUMBER($AB22)),OFFSET(RiskMatrixRef,-$AB22+1,AC22-1),"") | AH22: =IF(AND(ISNUMBER(AD22),ISNUMBER($AB22)),OFFSET(RiskMatrixRef,-$AB22+1,AD22-1),"") | AI22: =IF(AND(ISNUMBER(AE22),ISNUMBER($AB22)),OFFSET(RiskMatrixRef,-$AB22+1,AE22-1),"") | AJ22: =IF(AND(ISNUMBER(AF22),ISNUMBER($AB22)),OFFSET(RiskMatrixRef,-$AB22+1,AF22-1),"") | AS22: =IF(AND(ISNUMBER(AO22),ISNUMBER($AN22)),OFFSET(RiskMatrixRef,-$AN22+1,AO22-1),"") | AT22: =IF(AND(ISNUMBER(AP22),ISNUMBER($AN22)),OFFSET(RiskMatrixRef,-$AN22+1,AP22-1),"") | AU22: =IF(AND(ISNUMBER(AQ22),ISNUMBER($AN22)),OFFSET(RiskMatrixRef,-$AN22+1,AQ22-1),"") | AV22: =IF(AND(ISNUMBER(AR22),ISNUMBER($AN22)),OFFSET(RiskMatrixRef,-$AN22+1,AR22-1),"")
B23: 0113-2 0123-2 | C23: Fwd float idler arm Aft float idler arm | D23: Constrain float to relative pitch about nacelle | E23: 2 | F23: Loading in wave environment, with large motions | G23: Idler arm broken | H23: 1) Wave loading of float is no longer transferred nacelle tube on idler side 2) Addtl loading on drive arm | I23: Wearing of float arm, due to deflection | J23: Normal | K23: none | L23: Visual inspection, and repair if needed | M23: 1) Surveillance cameras | N23: Dry dock reattachment of float arm to WEC | O23: 7 | P23: 1 | Q23: 1 | R23: 6 | S23: 7 | T23: =IF(AND(ISNUMBER(P23),ISNUMBER($O23)),OFFSET(RiskMatrixRef,-$O23+1,P23-1),"") -> Low | U23: =IF(AND(ISNUMBER(Q23),ISNUMBER($O23)),OFFSET(RiskMatrixRef,-$O23+1,Q23-1),"") -> Low | V23: =IF(AND(ISNUMBER(R23),ISNUMBER($O23)),OFFSET(RiskMatrixRef,-$O23+1,R23-1),"") -> Med | W23: =IF(AND(ISNUMBER(S23),ISNUMBER($O23)),OFFSET(RiskMatrixRef,-$O23+1,S23-1),"") -> Med | X23: 1) Additional thickness to be considered in areas that wear could occur. 2) Identify the expected magnitude of wear and time to inspect / repair. 3) Specify inspection plan to be implemented after deployment. 4) Design to consider additional safety margin on space between components (where rubbing and wear is possible) to allow for uncertainty of loading and structural stiffness. | Y23: Suggest text for recommended action: Additional thickness to be considered in areas that wear could occur. Identify the magnitude of wear and time to inspect / repair. Inspection plan to be implemented after deployment. Design to consider addition safety margin on air gap to allow for uncertainty on loading and structural stiffness. | AG23: =IF(AND(ISNUMBER(AC23),ISNUMBER($AB23)),OFFSET(RiskMatrixRef,-$AB23+1,AC23-1),"") | AH23: =IF(AND(ISNUMBER(AD23),ISNUMBER($AB23)),OFFSET(RiskMatrixRef,-$AB23+1,AD23-1),"") | AI23: =IF(AND(ISNUMBER(AE23),ISNUMBER($AB23)),OFFSET(RiskMatrixRef,-$AB23+1,AE23-1),"") | AJ23: =IF(AND(ISNUMBER(AF23),ISNUMBER($AB23)),OFFSET(RiskMatrixRef,-$AB23+1,AF23-1),"") | AS23: =IF(AND(ISNUMBER(AO23),ISNUMBER($AN23)),OFFSET(RiskMatrixRef,-$AN23+1,AO23-1),"") | AT23: =IF(AND(ISNUMBER(AP23),ISNUMBER($AN23)),OFFSET(RiskMatrixRef,-$AN23+1,AP23-1),"") | AU23: =IF(AND(ISNUMBER(AQ23),ISNUMBER($AN23)),OFFSET(RiskMatrixRef,-$AN23+1,AQ23-1),"") | AV23: =IF(AND(ISNUMBER(AR23),ISNUMBER($AN23)),OFFSET(RiskMatrixRef,-$AN23+1,AR23-1),"")
B24: 0113-3 0123-3 | C24: Fwd float idler arm Aft float idler arm | D24: Constrain float to relative pitch about nacelle | E24: 2 | F24: Loading in wave environment, with large motions | G24: Idler arm broken | H24: 1) Wave loading of float is no longer transferred nacelle tube on idler side 2) Addtl loading on drive arm | I24: Non-service boat strike | J24: Normal | K24: 1) Lights, radar reflectors (e.g. visibility) | L24: none | M24: 1) Surveillance cameras | N24: Dry dock reattachment of float arm to WEC | O24: 4 | P24: 3 | Q24: 1 | R24: 6 | S24: 7 | T24: =IF(AND(ISNUMBER(P24),ISNUMBER($O24)),OFFSET(RiskMatrixRef,-$O24+1,P24-1),"") -> Low | U24: =IF(AND(ISNUMBER(Q24),ISNUMBER($O24)),OFFSET(RiskMatrixRef,-$O24+1,Q24-1),"") -> Low | V24: =IF(AND(ISNUMBER(R24),ISNUMBER($O24)),OFFSET(RiskMatrixRef,-$O24+1,R24-1),"") -> Low | W24: =IF(AND(ISNUMBER(S24),ISNUMBER($O24)),OFFSET(RiskMatrixRef,-$O24+1,S24-1),"") -> Low | X24: 1) establish exclusion zone at deployed area 2) The probability of occurrence to be verified considering conditions at the site and vessels in the area | Y24: The probability of occurrence to be verified considering conditions at the site and vessels in the area. | AG24: =IF(AND(ISNUMBER(AC24),ISNUMBER($AB24)),OFFSET(RiskMatrixRef,-$AB24+1,AC24-1),"") | AH24: =IF(AND(ISNUMBER(AD24),ISNUMBER($AB24)),OFFSET(RiskMatrixRef,-$AB24+1,AD24-1),"") | AI24: =IF(AND(ISNUMBER(AE24),ISNUMBER($AB24)),OFFSET(RiskMatrixRef,-$AB24+1,AE24-1),"") | AJ24: =IF(AND(ISNUMBER(AF24),ISNUMBER($AB24)),OFFSET(RiskMatrixRef,-$AB24+1,AF24-1),"") | AS24: =IF(AND(ISNUMBER(AO24),ISNUMBER($AN24)),OFFSET(RiskMatrixRef,-$AN24+1,AO24-1),"") | AT24: =IF(AND(ISNUMBER(AP24),ISNUMBER($AN24)),OFFSET(RiskMatrixRef,-$AN24+1,AP24-1),"") | AU24: =IF(AND(ISNUMBER(AQ24),ISNUMBER($AN24)),OFFSET(RiskMatrixRef,-$AN24+1,AQ24-1),"") | AV24: =IF(AND(ISNUMBER(AR24),ISNUMBER($AN24)),OFFSET(RiskMatrixRef,-$AN24+1,AR24-1),"")
B25: 0131-1 | C25: Nacelle Tube | D25: Rigid connection between nacelle assembly and spars Provide access pathway to nacelle Provision of watertight compartment Counterface for aft float (port) idler bearing (0265) | E25: 2 | F25: Loading in wave environment, with large motions | G25: Hole in single comparment | H25: 1) water ingress via hole 2) bilge removes water in nacelle tube and spar compartment | I25: Leak in FRP (e.g. manufacturing flaw, assembly) | J25: Normal | K25: 1) vacuum test all water tight compartments 2) Single empty compartment filling does not sink WEC 3) V&V for manufacturing and assembly 4) bilge pumps in every watertight compartment | M25: 1) bilge detection | N25: Repair in-situ | O25: 4 | P25: 1 | Q25: 1 | R25: 1 | S25: 3 | T25: =IF(AND(ISNUMBER(P25),ISNUMBER($O25)),OFFSET(RiskMatrixRef,-$O25+1,P25-1),"") -> Low | U25: =IF(AND(ISNUMBER(Q25),ISNUMBER($O25)),OFFSET(RiskMatrixRef,-$O25+1,Q25-1),"") -> Low | V25: =IF(AND(ISNUMBER(R25),ISNUMBER($O25)),OFFSET(RiskMatrixRef,-$O25+1,R25-1),"") -> Low | W25: =IF(AND(ISNUMBER(S25),ISNUMBER($O25)),OFFSET(RiskMatrixRef,-$O25+1,S25-1),"") -> Low | X25: 1) V&V procedures to be defined and followed, which shall mitigate risk of defective component up to commissioning. | Y25: See comment on failure effects and causes in 0111-1 | AG25: =IF(AND(ISNUMBER(AC25),ISNUMBER($AB25)),OFFSET(RiskMatrixRef,-$AB25+1,AC25-1),"") | AH25: =IF(AND(ISNUMBER(AD25),ISNUMBER($AB25)),OFFSET(RiskMatrixRef,-$AB25+1,AD25-1),"") | AI25: =IF(AND(ISNUMBER(AE25),ISNUMBER($AB25)),OFFSET(RiskMatrixRef,-$AB25+1,AE25-1),"") | AJ25: =IF(AND(ISNUMBER(AF25),ISNUMBER($AB25)),OFFSET(RiskMatrixRef,-$AB25+1,AF25-1),"") | AS25: =IF(AND(ISNUMBER(AO25),ISNUMBER($AN25)),OFFSET(RiskMatrixRef,-$AN25+1,AO25-1),"") | AT25: =IF(AND(ISNUMBER(AP25),ISNUMBER($AN25)),OFFSET(RiskMatrixRef,-$AN25+1,AP25-1),"") | AU25: =IF(AND(ISNUMBER(AQ25),ISNUMBER($AN25)),OFFSET(RiskMatrixRef,-$AN25+1,AQ25-1),"") | AV25: =IF(AND(ISNUMBER(AR25),ISNUMBER($AN25)),OFFSET(RiskMatrixRef,-$AN25+1,AR25-1),"") | AX25: non critical space bilge cost limit: 1/8 of bilge budget per spar compartment
B26: 0131-2 | C26: Nacelle Tube | D26: Rigid connection between nacelle assembly and spars Provide access pathway to nacelle Provision of watertight compartment Counterface for aft float (port) idler bearing (0265) | E26: 2 | F26: Loading in wave environment, with large motions | G26: Hole in single comparment | H26: 1) water ingress via hole 2) bilge removes water in nacelle tube and spar compartment | I26: Leak in FRP - fatigue crack due to uncertainties in loading | J26: Normal | K26: 1) Single empty compartment filling does not sink WEC 2) bilge pumps in every watertight compartment | M26: 1) bilge detection | N26: Dry dock for FRP repair and replacement of damaged components | O26: 7 | P26: 1 | Q26: 1 | R26: 6 | S26: 7 | T26: =IF(AND(ISNUMBER(P26),ISNUMBER($O26)),OFFSET(RiskMatrixRef,-$O26+1,P26-1),"") -> Low | U26: =IF(AND(ISNUMBER(Q26),ISNUMBER($O26)),OFFSET(RiskMatrixRef,-$O26+1,Q26-1),"") -> Low | V26: =IF(AND(ISNUMBER(R26),ISNUMBER($O26)),OFFSET(RiskMatrixRef,-$O26+1,R26-1),"") -> Med | W26: =IF(AND(ISNUMBER(S26),ISNUMBER($O26)),OFFSET(RiskMatrixRef,-$O26+1,S26-1),"") -> Med | X26: 1) Load derivation methodology to take into account the uncertainties in the loading due to site characterisation measurements and hydrodynamic modelling. 2) Uncertainty of loading estimates to be reduced by comparison of hydrodynamic behavior in simulation versus tank testing. 3) Design load cases to be defined considering all phases (e.g. operating w/ fault, installation, etc.), and to include investigation of localized loading from e.g. slamming. 4) Derivation of localized loading to be developed, and validated via instrumentation of prototype at-sea deployment. 5) Design fatigue factors (DFF) shall be applied to reduce probability of fatigue failure. 6) Establish inspection plan | Y26: See also comment on "improper design" (0111-1) Suggest text for recommended action Increase DFF For loading uncertainty and simulation accuracy see action for "Fatigue and other degradation mechanisms" for Hull. | AG26: =IF(AND(ISNUMBER(AC26),ISNUMBER($AB26)),OFFSET(RiskMatrixRef,-$AB26+1,AC26-1),"") | AH26: =IF(AND(ISNUMBER(AD26),ISNUMBER($AB26)),OFFSET(RiskMatrixRef,-$AB26+1,AD26-1),"") | AI26: =IF(AND(ISNUMBER(AE26),ISNUMBER($AB26)),OFFSET(RiskMatrixRef,-$AB26+1,AE26-1),"") | AJ26: =IF(AND(ISNUMBER(AF26),ISNUMBER($AB26)),OFFSET(RiskMatrixRef,-$AB26+1,AF26-1),"") | AS26: =IF(AND(ISNUMBER(AO26),ISNUMBER($AN26)),OFFSET(RiskMatrixRef,-$AN26+1,AO26-1),"") | AT26: =IF(AND(ISNUMBER(AP26),ISNUMBER($AN26)),OFFSET(RiskMatrixRef,-$AN26+1,AP26-1),"") | AU26: =IF(AND(ISNUMBER(AQ26),ISNUMBER($AN26)),OFFSET(RiskMatrixRef,-$AN26+1,AQ26-1),"") | AV26: =IF(AND(ISNUMBER(AR26),ISNUMBER($AN26)),OFFSET(RiskMatrixRef,-$AN26+1,AR26-1),"") | AX26: non critical space bilge cost limit: 1/8 of bilge budget per spar compartment
B27: 0132-1 | C27: Lower Nacelle | D27: Provision of watertight compartment | E27: 2 | F27: Loading in wave environment, with large motions | G27: Hole in single compartment | H27: Crack/hole in hull (No water ingress/egress) | I27: Leak in FRP (e.g. manufacturing flaw, assembly) | J27: Normal | K27: 1) No empty voids (full of foam) 2) vacuum test all water tight compartments 3) V&V for manufacturing and assembly 4) bilge pumps in every watertight compartment | M27: No detection | N27: No repair necessary | O27: 4 | P27: 1 | Q27: 1 | R27: 1 | S27: 1 | T27: =IF(AND(ISNUMBER(P27),ISNUMBER($O27)),OFFSET(RiskMatrixRef,-$O27+1,P27-1),"") -> Low | U27: =IF(AND(ISNUMBER(Q27),ISNUMBER($O27)),OFFSET(RiskMatrixRef,-$O27+1,Q27-1),"") -> Low | V27: =IF(AND(ISNUMBER(R27),ISNUMBER($O27)),OFFSET(RiskMatrixRef,-$O27+1,R27-1),"") -> Low | W27: =IF(AND(ISNUMBER(S27),ISNUMBER($O27)),OFFSET(RiskMatrixRef,-$O27+1,S27-1),"") -> Low | X27: 1) V&V procedures to be defined and followed, which shall mitigate risk of defective component up to commissioning. 2) Design to specify allowable water absorption (and degree of degradation due to water contact) of foam. | Y27: See comment on failure effects and causes in 0111-1 | AG27: =IF(AND(ISNUMBER(AC27),ISNUMBER($AB27)),OFFSET(RiskMatrixRef,-$AB27+1,AC27-1),"") | AH27: =IF(AND(ISNUMBER(AD27),ISNUMBER($AB27)),OFFSET(RiskMatrixRef,-$AB27+1,AD27-1),"") | AI27: =IF(AND(ISNUMBER(AE27),ISNUMBER($AB27)),OFFSET(RiskMatrixRef,-$AB27+1,AE27-1),"") | AJ27: =IF(AND(ISNUMBER(AF27),ISNUMBER($AB27)),OFFSET(RiskMatrixRef,-$AB27+1,AF27-1),"") | AS27: =IF(AND(ISNUMBER(AO27),ISNUMBER($AN27)),OFFSET(RiskMatrixRef,-$AN27+1,AO27-1),"") | AT27: =IF(AND(ISNUMBER(AP27),ISNUMBER($AN27)),OFFSET(RiskMatrixRef,-$AN27+1,AP27-1),"") | AU27: =IF(AND(ISNUMBER(AQ27),ISNUMBER($AN27)),OFFSET(RiskMatrixRef,-$AN27+1,AQ27-1),"") | AV27: =IF(AND(ISNUMBER(AR27),ISNUMBER($AN27)),OFFSET(RiskMatrixRef,-$AN27+1,AR27-1),"") | AX27: EDR specify foam does not allow greater than X% of water absorption Cohesive foam
B28: 0132-2 | C28: Lower Nacelle | D28: Provision of watertight compartment | E28: 2 | F28: Loading in wave environment, with large motions | G28: Hole in single compartment | H28: Crack/hole in hull (No water ingress/egress) | I28: Leak in FRP - fatigue crack due to uncertainties in loading | J28: Normal | K28: 1) No empty voids (full of foam) 2) Single empty compartment filling does not sink WEC 3) bilge pumps in every watertight compartment | M28: No detection | N28: No repair necessary | O28: 5 | P28: 1 | Q28: 1 | R28: 1 | S28: 1 | T28: =IF(AND(ISNUMBER(P28),ISNUMBER($O28)),OFFSET(RiskMatrixRef,-$O28+1,P28-1),"") -> Low | U28: =IF(AND(ISNUMBER(Q28),ISNUMBER($O28)),OFFSET(RiskMatrixRef,-$O28+1,Q28-1),"") -> Low | V28: =IF(AND(ISNUMBER(R28),ISNUMBER($O28)),OFFSET(RiskMatrixRef,-$O28+1,R28-1),"") -> Low | W28: =IF(AND(ISNUMBER(S28),ISNUMBER($O28)),OFFSET(RiskMatrixRef,-$O28+1,S28-1),"") -> Low | X28: 1) Load derivation methodology to take into account the uncertainties in the loading due to site characterisation measurements and hydrodynamic modelling. 2) Uncertainty of loading estimates to be reduced by comparison of hydrodynamic behavior in simulation versus tank testing. 3) Design load cases to be defined considering all phases (e.g. operating w/ fault, installation, etc.), and to include investigation of localized loading from e.g. slamming. 4) Derivation of localized loading to be developed, and validated via instrumentation of prototype at-sea deployment. 5) Design fatigue factors (DFF) shall be applied to reduce probability of fatigue failure. 6) Establish inspection plan 7) Design to specify allowable water absorption (and degree of degradation due to water contact) of foam. | Y28: See also comment on "improper design" (0111-1) Action the same as "Leak in FRP - fatigue crack due to improper design" for Nacelle Tube | AG28: =IF(AND(ISNUMBER(AC28),ISNUMBER($AB28)),OFFSET(RiskMatrixRef,-$AB28+1,AC28-1),"") | AH28: =IF(AND(ISNUMBER(AD28),ISNUMBER($AB28)),OFFSET(RiskMatrixRef,-$AB28+1,AD28-1),"") | AI28: =IF(AND(ISNUMBER(AE28),ISNUMBER($AB28)),OFFSET(RiskMatrixRef,-$AB28+1,AE28-1),"") | AJ28: =IF(AND(ISNUMBER(AF28),ISNUMBER($AB28)),OFFSET(RiskMatrixRef,-$AB28+1,AF28-1),"") | AS28: =IF(AND(ISNUMBER(AO28),ISNUMBER($AN28)),OFFSET(RiskMatrixRef,-$AN28+1,AO28-1),"") | AT28: =IF(AND(ISNUMBER(AP28),ISNUMBER($AN28)),OFFSET(RiskMatrixRef,-$AN28+1,AP28-1),"") | AU28: =IF(AND(ISNUMBER(AQ28),ISNUMBER($AN28)),OFFSET(RiskMatrixRef,-$AN28+1,AQ28-1),"") | AV28: =IF(AND(ISNUMBER(AR28),ISNUMBER($AN28)),OFFSET(RiskMatrixRef,-$AN28+1,AR28-1),"") | AX28: EDR specify foam does not allow greater than X% of water absorption Cohesive foam
B29: 0133-1 0134-1 | C29: PTO Hull - STBD PTO Hull - PORT | D29: Provision of watertight compartment | E29: 2 | F29: Loading in wave environment, with large motions | G29: Hole in single comparment | H29: 1) water ingress through hole (bilge removes water from compartment) | I29: Leak in FRP (e.g. manufacturing flaw, assembly) | J29: Normal | K29: 1) vacuum test all water tight compartments 2) Single empty compartment filling does not sink WEC 3) V&V for manufacturing and assembly 4) bilge pumps in every watertight compartment | M29: 1) bilge detection | N29: Repair in-situ | O29: 3 | P29: 1 | Q29: 1 | R29: 1 | S29: 3 | T29: =IF(AND(ISNUMBER(P29),ISNUMBER($O29)),OFFSET(RiskMatrixRef,-$O29+1,P29-1),"") -> Low | U29: =IF(AND(ISNUMBER(Q29),ISNUMBER($O29)),OFFSET(RiskMatrixRef,-$O29+1,Q29-1),"") -> Low | V29: =IF(AND(ISNUMBER(R29),ISNUMBER($O29)),OFFSET(RiskMatrixRef,-$O29+1,R29-1),"") -> Low | W29: =IF(AND(ISNUMBER(S29),ISNUMBER($O29)),OFFSET(RiskMatrixRef,-$O29+1,S29-1),"") -> Low | X29: 1) V&V procedures to be defined and followed, which shall mitigate risk of defective component up to commissioning. | Y29: See comment on failure effects and causes in 0111-1 | AG29: =IF(AND(ISNUMBER(AC29),ISNUMBER($AB29)),OFFSET(RiskMatrixRef,-$AB29+1,AC29-1),"") | AH29: =IF(AND(ISNUMBER(AD29),ISNUMBER($AB29)),OFFSET(RiskMatrixRef,-$AB29+1,AD29-1),"") | AI29: =IF(AND(ISNUMBER(AE29),ISNUMBER($AB29)),OFFSET(RiskMatrixRef,-$AB29+1,AE29-1),"") | AJ29: =IF(AND(ISNUMBER(AF29),ISNUMBER($AB29)),OFFSET(RiskMatrixRef,-$AB29+1,AF29-1),"") | AS29: =IF(AND(ISNUMBER(AO29),ISNUMBER($AN29)),OFFSET(RiskMatrixRef,-$AN29+1,AO29-1),"") | AT29: =IF(AND(ISNUMBER(AP29),ISNUMBER($AN29)),OFFSET(RiskMatrixRef,-$AN29+1,AP29-1),"") | AU29: =IF(AND(ISNUMBER(AQ29),ISNUMBER($AN29)),OFFSET(RiskMatrixRef,-$AN29+1,AQ29-1),"") | AV29: =IF(AND(ISNUMBER(AR29),ISNUMBER($AN29)),OFFSET(RiskMatrixRef,-$AN29+1,AR29-1),"")
B30: 0133-2 0134-2 | C30: PTO Hull - STBD PTO Hull - PORT | D30: Provision of watertight compartment | E30: 2 | F30: Loading in wave environment, with large motions | G30: Hole in single comparment | H30: 1) water ingress through hole (bilge removes water from compartment) | I30: Leak in FRP - fatigue crack due to uncertainties in loading | J30: Normal | K30: 1) Single empty compartment filling does not sink WEC 2) bilge pumps in every watertight compartment | M30: 1) bilge detection | N30: Dry dock for FRP repair and replacement of damaged components | O30: 7 | P30: 1 | Q30: 1 | R30: 1 | S30: 7 | T30: =IF(AND(ISNUMBER(P30),ISNUMBER($O30)),OFFSET(RiskMatrixRef,-$O30+1,P30-1),"") -> Low | U30: =IF(AND(ISNUMBER(Q30),ISNUMBER($O30)),OFFSET(RiskMatrixRef,-$O30+1,Q30-1),"") -> Low | V30: =IF(AND(ISNUMBER(R30),ISNUMBER($O30)),OFFSET(RiskMatrixRef,-$O30+1,R30-1),"") -> Low | W30: =IF(AND(ISNUMBER(S30),ISNUMBER($O30)),OFFSET(RiskMatrixRef,-$O30+1,S30-1),"") -> Med | X30: 1) Load derivation methodology to take into account the uncertainties in the loading due to site characterisation measurements and hydrodynamic modelling. 2) Uncertainty of loading estimates to be reduced by comparison of hydrodynamic behavior in simulation versus tank testing. 3) Design load cases to be defined considering all phases (e.g. operating w/ fault, installation, etc.), and to include investigation of localized loading from e.g. slamming. 4) Derivation of localized loading to be developed, and validated via instrumentation of prototype at-sea deployment. 5) Design fatigue factors (DFF) shall be applied to reduce probability of fatigue failure. 6) Establish inspection plan | Y30: See also comment on "improper design" (0111-1) Action the same as "Leak in FRP - fatigue crack due to improper design" for Nacelle Tube For loading uncertainty and simulation accuracy, see action on "Extreme wave event loading" in HULL | AG30: =IF(AND(ISNUMBER(AC30),ISNUMBER($AB30)),OFFSET(RiskMatrixRef,-$AB30+1,AC30-1),"") | AH30: =IF(AND(ISNUMBER(AD30),ISNUMBER($AB30)),OFFSET(RiskMatrixRef,-$AB30+1,AD30-1),"") | AI30: =IF(AND(ISNUMBER(AE30),ISNUMBER($AB30)),OFFSET(RiskMatrixRef,-$AB30+1,AE30-1),"") | AJ30: =IF(AND(ISNUMBER(AF30),ISNUMBER($AB30)),OFFSET(RiskMatrixRef,-$AB30+1,AF30-1),"") | AS30: =IF(AND(ISNUMBER(AO30),ISNUMBER($AN30)),OFFSET(RiskMatrixRef,-$AN30+1,AO30-1),"") | AT30: =IF(AND(ISNUMBER(AP30),ISNUMBER($AN30)),OFFSET(RiskMatrixRef,-$AN30+1,AP30-1),"") | AU30: =IF(AND(ISNUMBER(AQ30),ISNUMBER($AN30)),OFFSET(RiskMatrixRef,-$AN30+1,AQ30-1),"") | AV30: =IF(AND(ISNUMBER(AR30),ISNUMBER($AN30)),OFFSET(RiskMatrixRef,-$AN30+1,AR30-1),"")
B31: 0133-3 0134-3 | C31: PTO Hull - STBD PTO Hull - PORT | D31: Provision of watertight compartment | E31: 2 | F31: Loading in wave environment, with large motions | G31: Hole in single comparment | H31: 1) water ingress through hole (bilge removes water from compartment) | I31: Non-service boat strike (float overtopping required) | J31: Normal | K31: 1) lights, Radar reflectors (visibility) 2) Single empty compartment filling does not sink WEC 3) bilge pumps in every watertight compartment | M31: 1) bilge detection | N31: In situ FRP repair if possible (hole above waterline and known location) Worst case: Dry dock inspection and repair of WEC. | O31: 3 | P31: 3 | Q31: 1 | R31: 6 | S31: 7 | T31: =IF(AND(ISNUMBER(P31),ISNUMBER($O31)),OFFSET(RiskMatrixRef,-$O31+1,P31-1),"") -> Low | U31: =IF(AND(ISNUMBER(Q31),ISNUMBER($O31)),OFFSET(RiskMatrixRef,-$O31+1,Q31-1),"") -> Low | V31: =IF(AND(ISNUMBER(R31),ISNUMBER($O31)),OFFSET(RiskMatrixRef,-$O31+1,R31-1),"") -> Low | W31: =IF(AND(ISNUMBER(S31),ISNUMBER($O31)),OFFSET(RiskMatrixRef,-$O31+1,S31-1),"") -> Low | X31: 1) establish exclusion zone at deployed area 2) The probability of occurrence to be verified considering conditions at the site and vessels in the area | Y31: The probability of occurrence to be verified considering conditions at the site and vessels in the area. | AG31: =IF(AND(ISNUMBER(AC31),ISNUMBER($AB31)),OFFSET(RiskMatrixRef,-$AB31+1,AC31-1),"") | AH31: =IF(AND(ISNUMBER(AD31),ISNUMBER($AB31)),OFFSET(RiskMatrixRef,-$AB31+1,AD31-1),"") | AI31: =IF(AND(ISNUMBER(AE31),ISNUMBER($AB31)),OFFSET(RiskMatrixRef,-$AB31+1,AE31-1),"") | AJ31: =IF(AND(ISNUMBER(AF31),ISNUMBER($AB31)),OFFSET(RiskMatrixRef,-$AB31+1,AF31-1),"") | AS31: =IF(AND(ISNUMBER(AO31),ISNUMBER($AN31)),OFFSET(RiskMatrixRef,-$AN31+1,AO31-1),"") | AT31: =IF(AND(ISNUMBER(AP31),ISNUMBER($AN31)),OFFSET(RiskMatrixRef,-$AN31+1,AP31-1),"") | AU31: =IF(AND(ISNUMBER(AQ31),ISNUMBER($AN31)),OFFSET(RiskMatrixRef,-$AN31+1,AQ31-1),"") | AV31: =IF(AND(ISNUMBER(AR31),ISNUMBER($AN31)),OFFSET(RiskMatrixRef,-$AN31+1,AR31-1),"")
B32: 0135-1 | C32: Control Room | D32: Provision of watertight compartment | E32: 2 | F32: Loading in wave environment, with large motions | G32: Hole in single comparment | H32: 1) water ingress through hole (bilge removes water from compartment) | I32: Leak in FRP (e.g. manufacturing flaw, assembly) not boat strikes | J32: Normal | K32: 1) vacuum test all water tight compartments 2) Single empty compartment filling does not sink WEC 3) V&V for manufacturing and assembly 4) bilge pumps in every watertight compartment | M32: 1) bilge detection | N32: Repair in-situ | O32: 3 | P32: 1 | Q32: 1 | R32: 1 | S32: 3 | T32: =IF(AND(ISNUMBER(P32),ISNUMBER($O32)),OFFSET(RiskMatrixRef,-$O32+1,P32-1),"") -> Low | U32: =IF(AND(ISNUMBER(Q32),ISNUMBER($O32)),OFFSET(RiskMatrixRef,-$O32+1,Q32-1),"") -> Low | V32: =IF(AND(ISNUMBER(R32),ISNUMBER($O32)),OFFSET(RiskMatrixRef,-$O32+1,R32-1),"") -> Low | W32: =IF(AND(ISNUMBER(S32),ISNUMBER($O32)),OFFSET(RiskMatrixRef,-$O32+1,S32-1),"") -> Low | X32: 1) V&V procedures to be defined and followed, which shall mitigate risk of defective component up to commissioning. | Y32: See comment on failure effects and causes in 0111-1 | AG32: =IF(AND(ISNUMBER(AC32),ISNUMBER($AB32)),OFFSET(RiskMatrixRef,-$AB32+1,AC32-1),"") | AH32: =IF(AND(ISNUMBER(AD32),ISNUMBER($AB32)),OFFSET(RiskMatrixRef,-$AB32+1,AD32-1),"") | AI32: =IF(AND(ISNUMBER(AE32),ISNUMBER($AB32)),OFFSET(RiskMatrixRef,-$AB32+1,AE32-1),"") | AJ32: =IF(AND(ISNUMBER(AF32),ISNUMBER($AB32)),OFFSET(RiskMatrixRef,-$AB32+1,AF32-1),"") | AS32: =IF(AND(ISNUMBER(AO32),ISNUMBER($AN32)),OFFSET(RiskMatrixRef,-$AN32+1,AO32-1),"") | AT32: =IF(AND(ISNUMBER(AP32),ISNUMBER($AN32)),OFFSET(RiskMatrixRef,-$AN32+1,AP32-1),"") | AU32: =IF(AND(ISNUMBER(AQ32),ISNUMBER($AN32)),OFFSET(RiskMatrixRef,-$AN32+1,AQ32-1),"") | AV32: =IF(AND(ISNUMBER(AR32),ISNUMBER($AN32)),OFFSET(RiskMatrixRef,-$AN32+1,AR32-1),"")
B33: 0135-2 | C33: Control Room | D33: Provision of watertight compartment | E33: 2 | F33: Loading in wave environment, with large motions | G33: Hole in single comparment | H33: 1) water ingress through hole (bilge removes water from compartment) | I33: Leak in FRP - fatigue crack due to uncertainties in loading | J33: Normal | K33: 1) Single empty compartment filling does not sink WEC 2) bilge pumps in every watertight compartment | M33: 1) bilge detection | N33: Dry dock for FRP repair and replacement of damaged components | O33: 4 | P33: 1 | Q33: 1 | R33: 1 | S33: 7 | T33: =IF(AND(ISNUMBER(P33),ISNUMBER($O33)),OFFSET(RiskMatrixRef,-$O33+1,P33-1),"") -> Low | U33: =IF(AND(ISNUMBER(Q33),ISNUMBER($O33)),OFFSET(RiskMatrixRef,-$O33+1,Q33-1),"") -> Low | V33: =IF(AND(ISNUMBER(R33),ISNUMBER($O33)),OFFSET(RiskMatrixRef,-$O33+1,R33-1),"") -> Low | W33: =IF(AND(ISNUMBER(S33),ISNUMBER($O33)),OFFSET(RiskMatrixRef,-$O33+1,S33-1),"") -> Low | X33: 1) Load derivation methodology to take into account the uncertainties in the loading due to site characterisation measurements and hydrodynamic modelling. 2) Uncertainty of loading estimates to be reduced by comparison of hydrodynamic behavior in simulation versus tank testing. 3) Design load cases to be defined considering all phases (e.g. operating w/ fault, installation, etc.), and to include investigation of localized loading from e.g. slamming. 4) Derivation of localized loading to be developed, and validated via instrumentation of prototype at-sea deployment. 5) Design fatigue factors (DFF) shall be applied to reduce probability of fatigue failure. 6) Establish inspection plan | Y33: See also comment on "improper design" (0111-1) Action the same as "Leak in FRP - fatigue crack due to improper design" for Nacelle Tube | AG33: =IF(AND(ISNUMBER(AC33),ISNUMBER($AB33)),OFFSET(RiskMatrixRef,-$AB33+1,AC33-1),"") | AH33: =IF(AND(ISNUMBER(AD33),ISNUMBER($AB33)),OFFSET(RiskMatrixRef,-$AB33+1,AD33-1),"") | AI33: =IF(AND(ISNUMBER(AE33),ISNUMBER($AB33)),OFFSET(RiskMatrixRef,-$AB33+1,AE33-1),"") | AJ33: =IF(AND(ISNUMBER(AF33),ISNUMBER($AB33)),OFFSET(RiskMatrixRef,-$AB33+1,AF33-1),"") | AS33: =IF(AND(ISNUMBER(AO33),ISNUMBER($AN33)),OFFSET(RiskMatrixRef,-$AN33+1,AO33-1),"") | AT33: =IF(AND(ISNUMBER(AP33),ISNUMBER($AN33)),OFFSET(RiskMatrixRef,-$AN33+1,AP33-1),"") | AU33: =IF(AND(ISNUMBER(AQ33),ISNUMBER($AN33)),OFFSET(RiskMatrixRef,-$AN33+1,AQ33-1),"") | AV33: =IF(AND(ISNUMBER(AR33),ISNUMBER($AN33)),OFFSET(RiskMatrixRef,-$AN33+1,AR33-1),"")
B34: 0135-3 | C34: Control Room | D34: Provision of watertight compartment | E34: 2 | F34: Loading in wave environment, with large motions | G34: Hole in single comparment | H34: 1) water ingress through hole (bilge removes water from compartment) | I34: Non-service boat strike | J34: Normal | K34: 1) lights, Radar reflectors (visibility) 2) Single empty compartment filling does not sink WEC 3) bilge pumps in every watertight compartment | M34: 1) bilge detection | N34: In situ FRP repair if possible (hole above waterline and known location) Worst case: Dry dock inspection and repair of WEC. | O34: 3 | P34: 3 | Q34: 1 | R34: 6 | S34: 7 | T34: =IF(AND(ISNUMBER(P34),ISNUMBER($O34)),OFFSET(RiskMatrixRef,-$O34+1,P34-1),"") -> Low | U34: =IF(AND(ISNUMBER(Q34),ISNUMBER($O34)),OFFSET(RiskMatrixRef,-$O34+1,Q34-1),"") -> Low | V34: =IF(AND(ISNUMBER(R34),ISNUMBER($O34)),OFFSET(RiskMatrixRef,-$O34+1,R34-1),"") -> Low | W34: =IF(AND(ISNUMBER(S34),ISNUMBER($O34)),OFFSET(RiskMatrixRef,-$O34+1,S34-1),"") -> Low | X34: 1) establish exclusion zone at deployed area 2) The probability of occurrence to be verified considering conditions at the site and vessels in the area | Y34: The probability of occurrence to be verified considering conditions at the site and vessels in the area. | AG34: =IF(AND(ISNUMBER(AC34),ISNUMBER($AB34)),OFFSET(RiskMatrixRef,-$AB34+1,AC34-1),"") | AH34: =IF(AND(ISNUMBER(AD34),ISNUMBER($AB34)),OFFSET(RiskMatrixRef,-$AB34+1,AD34-1),"") | AI34: =IF(AND(ISNUMBER(AE34),ISNUMBER($AB34)),OFFSET(RiskMatrixRef,-$AB34+1,AE34-1),"") | AJ34: =IF(AND(ISNUMBER(AF34),ISNUMBER($AB34)),OFFSET(RiskMatrixRef,-$AB34+1,AF34-1),"") | AS34: =IF(AND(ISNUMBER(AO34),ISNUMBER($AN34)),OFFSET(RiskMatrixRef,-$AN34+1,AO34-1),"") | AT34: =IF(AND(ISNUMBER(AP34),ISNUMBER($AN34)),OFFSET(RiskMatrixRef,-$AN34+1,AP34-1),"") | AU34: =IF(AND(ISNUMBER(AQ34),ISNUMBER($AN34)),OFFSET(RiskMatrixRef,-$AN34+1,AQ34-1),"") | AV34: =IF(AND(ISNUMBER(AR34),ISNUMBER($AN34)),OFFSET(RiskMatrixRef,-$AN34+1,AR34-1),"")
B35: 0141-1 0142-1 | C35: Spar - STBD Spar - PORT | D35: Rigid connection between nacelle tube and damper Dry access route into nacelle tubes Provision of watertight compartment | E35: 2 | F35: Loading in wave environment, with large motions | G35: Hole in single comparment | H35: 1) water ingress through hole (bilge removes water from compartment) | I35: Leak in FRP (e.g. manufacturing flaw, assembly) not boat strikes | J35: Normal | K35: 1) vacuum test all water tight compartments 2) Single empty compartment filling does not sink WEC 3) V&V for manufacturing and assembly 4) bilge pumps in every watertight compartment | M35: 1) bilge detection | N35: Repair in-situ | O35: 4 | P35: 1 | Q35: 1 | R35: 1 | S35: 3 | T35: =IF(AND(ISNUMBER(P35),ISNUMBER($O35)),OFFSET(RiskMatrixRef,-$O35+1,P35-1),"") -> Low | U35: =IF(AND(ISNUMBER(Q35),ISNUMBER($O35)),OFFSET(RiskMatrixRef,-$O35+1,Q35-1),"") -> Low | V35: =IF(AND(ISNUMBER(R35),ISNUMBER($O35)),OFFSET(RiskMatrixRef,-$O35+1,R35-1),"") -> Low | W35: =IF(AND(ISNUMBER(S35),ISNUMBER($O35)),OFFSET(RiskMatrixRef,-$O35+1,S35-1),"") -> Low | X35: 1) V&V procedures to be defined and followed, which shall mitigate risk of defective component up to commissioning. | Y35: See comment on failure effects and causes in 0111-1 | AG35: =IF(AND(ISNUMBER(AC35),ISNUMBER($AB35)),OFFSET(RiskMatrixRef,-$AB35+1,AC35-1),"") | AH35: =IF(AND(ISNUMBER(AD35),ISNUMBER($AB35)),OFFSET(RiskMatrixRef,-$AB35+1,AD35-1),"") | AI35: =IF(AND(ISNUMBER(AE35),ISNUMBER($AB35)),OFFSET(RiskMatrixRef,-$AB35+1,AE35-1),"") | AJ35: =IF(AND(ISNUMBER(AF35),ISNUMBER($AB35)),OFFSET(RiskMatrixRef,-$AB35+1,AF35-1),"") | AS35: =IF(AND(ISNUMBER(AO35),ISNUMBER($AN35)),OFFSET(RiskMatrixRef,-$AN35+1,AO35-1),"") | AT35: =IF(AND(ISNUMBER(AP35),ISNUMBER($AN35)),OFFSET(RiskMatrixRef,-$AN35+1,AP35-1),"") | AU35: =IF(AND(ISNUMBER(AQ35),ISNUMBER($AN35)),OFFSET(RiskMatrixRef,-$AN35+1,AQ35-1),"") | AV35: =IF(AND(ISNUMBER(AR35),ISNUMBER($AN35)),OFFSET(RiskMatrixRef,-$AN35+1,AR35-1),"")
B36: 0141-2 0142-2 | C36: Spar - STBD Spar - PORT | D36: Rigid connection between nacelle tube and damper Dry access route into nacelle tubes Provision of watertight compartment | E36: 2 | F36: Loading in wave environment, with large motions | G36: Hole in single comparment | H36: 1) water ingress through hole (bilge removes water from compartment) | I36: Leak in FRP - fatigue crack due to uncertainties in loading | J36: Normal | K36: 1) Single empty compartment filling does not sink WEC 2) bilge pumps in every watertight compartment | M36: 1) IMU orientation 2) pressure sensors outside attached to spars 3) bilge detection | N36: Dry dock for FRP repair and replacement of damaged components | O36: 5 | P36: 1 | Q36: 1 | R36: 6 | S36: 7 | T36: =IF(AND(ISNUMBER(P36),ISNUMBER($O36)),OFFSET(RiskMatrixRef,-$O36+1,P36-1),"") -> Low | U36: =IF(AND(ISNUMBER(Q36),ISNUMBER($O36)),OFFSET(RiskMatrixRef,-$O36+1,Q36-1),"") -> Low | V36: =IF(AND(ISNUMBER(R36),ISNUMBER($O36)),OFFSET(RiskMatrixRef,-$O36+1,R36-1),"") -> Low | W36: =IF(AND(ISNUMBER(S36),ISNUMBER($O36)),OFFSET(RiskMatrixRef,-$O36+1,S36-1),"") -> Med | X36: 1) Load derivation methodology to take into account the uncertainties in the loading due to site characterisation measurements and hydrodynamic modelling. 2) Uncertainty of loading estimates to be reduced by comparison of hydrodynamic behavior in simulation versus tank testing. 3) Design load cases to be defined considering all phases (e.g. operating w/ fault, installation, etc.), and to include investigation of localized loading from e.g. slamming. 4) Derivation of localized loading to be developed, and validated via instrumentation of prototype at-sea deployment. 5) Design fatigue factors (DFF) shall be applied to reduce probability of fatigue failure. 6) Establish inspection plan | Y36: See also comment on "improper design" (0111-1) Action the same as "Leak in FRP - fatigue crack due to improper design" for Nacelle Tube | AG36: =IF(AND(ISNUMBER(AC36),ISNUMBER($AB36)),OFFSET(RiskMatrixRef,-$AB36+1,AC36-1),"") | AH36: =IF(AND(ISNUMBER(AD36),ISNUMBER($AB36)),OFFSET(RiskMatrixRef,-$AB36+1,AD36-1),"") | AI36: =IF(AND(ISNUMBER(AE36),ISNUMBER($AB36)),OFFSET(RiskMatrixRef,-$AB36+1,AE36-1),"") | AJ36: =IF(AND(ISNUMBER(AF36),ISNUMBER($AB36)),OFFSET(RiskMatrixRef,-$AB36+1,AF36-1),"") | AS36: =IF(AND(ISNUMBER(AO36),ISNUMBER($AN36)),OFFSET(RiskMatrixRef,-$AN36+1,AO36-1),"") | AT36: =IF(AND(ISNUMBER(AP36),ISNUMBER($AN36)),OFFSET(RiskMatrixRef,-$AN36+1,AP36-1),"") | AU36: =IF(AND(ISNUMBER(AQ36),ISNUMBER($AN36)),OFFSET(RiskMatrixRef,-$AN36+1,AQ36-1),"") | AV36: =IF(AND(ISNUMBER(AR36),ISNUMBER($AN36)),OFFSET(RiskMatrixRef,-$AN36+1,AR36-1),"")
B37: 0141-3 0142-3 | C37: Spar - STBD Spar - PORT | D37: Rigid connection between nacelle tube and damper Dry access route into nacelle tubes Provision of watertight compartment | E37: 2 | F37: Loading in wave environment, with large motions | G37: Hole in single comparment | H37: 1) water ingress through hole (bilge removes water from compartment) | I37: Non-service Boat Strike | J37: Normal | K37: 1) lights, Radar reflectors (visibility) 2) Single empty compartment filling does not sink WEC 3) bilge pumps in every watertight compartment | M37: 1) Surveillance cameras 2) visual inspection 3) level sensors on spars | N37: In situ FRP repair if possible (hole above waterline and known location) Worst case: Dry dock inspection and repair of WEC. | O37: 8 | P37: 2 | Q37: 1 | R37: 6 | S37: 7 | T37: =IF(AND(ISNUMBER(P37),ISNUMBER($O37)),OFFSET(RiskMatrixRef,-$O37+1,P37-1),"") -> Low | U37: =IF(AND(ISNUMBER(Q37),ISNUMBER($O37)),OFFSET(RiskMatrixRef,-$O37+1,Q37-1),"") -> Low | V37: =IF(AND(ISNUMBER(R37),ISNUMBER($O37)),OFFSET(RiskMatrixRef,-$O37+1,R37-1),"") -> Med | W37: =IF(AND(ISNUMBER(S37),ISNUMBER($O37)),OFFSET(RiskMatrixRef,-$O37+1,S37-1),"") -> Med | X37: 1) establish exclusion zone at deployed area 2) The probability of occurrence to be verified considering conditions at the site and vessels in the area | Y37: Action the same as "Non-service Boat Strike" for Forward float/Aft Float | AG37: =IF(AND(ISNUMBER(AC37),ISNUMBER($AB37)),OFFSET(RiskMatrixRef,-$AB37+1,AC37-1),"") | AH37: =IF(AND(ISNUMBER(AD37),ISNUMBER($AB37)),OFFSET(RiskMatrixRef,-$AB37+1,AD37-1),"") | AI37: =IF(AND(ISNUMBER(AE37),ISNUMBER($AB37)),OFFSET(RiskMatrixRef,-$AB37+1,AE37-1),"") | AJ37: =IF(AND(ISNUMBER(AF37),ISNUMBER($AB37)),OFFSET(RiskMatrixRef,-$AB37+1,AF37-1),"") | AS37: =IF(AND(ISNUMBER(AO37),ISNUMBER($AN37)),OFFSET(RiskMatrixRef,-$AN37+1,AO37-1),"") | AT37: =IF(AND(ISNUMBER(AP37),ISNUMBER($AN37)),OFFSET(RiskMatrixRef,-$AN37+1,AP37-1),"") | AU37: =IF(AND(ISNUMBER(AQ37),ISNUMBER($AN37)),OFFSET(RiskMatrixRef,-$AN37+1,AQ37-1),"") | AV37: =IF(AND(ISNUMBER(AR37),ISNUMBER($AN37)),OFFSET(RiskMatrixRef,-$AN37+1,AR37-1),"")
B38: 0141-4 0142-4 | C38: Spar - STBD Spar - PORT | D38: Rigid connection between nacelle tube and damper Dry access route into nacelle tubes Provision of watertight compartment | E38: 2 | F38: Loading in wave environment, with large motions | G38: Hole in single comparment | H38: 1) water ingress through hole (bilge removes water from compartment) | I38: Service Boat Strike | J38: Normal | K38: 1) Single empty compartment filling does not sink WEC 2) bilge pumps in every watertight compartment | M38: 1) Surveillance cameras 2) visual inspection 3) level sensors on spars | N38: In situ FRP repair if possible (hole above waterline and known location) Worst case: Dry dock inspection and repair of WEC. | O38: 5 | P38: 2 | Q38: 1 | R38: 6 | S38: 7 | T38: =IF(AND(ISNUMBER(P38),ISNUMBER($O38)),OFFSET(RiskMatrixRef,-$O38+1,P38-1),"") -> Low | U38: =IF(AND(ISNUMBER(Q38),ISNUMBER($O38)),OFFSET(RiskMatrixRef,-$O38+1,Q38-1),"") -> Low | V38: =IF(AND(ISNUMBER(R38),ISNUMBER($O38)),OFFSET(RiskMatrixRef,-$O38+1,R38-1),"") -> Low | W38: =IF(AND(ISNUMBER(S38),ISNUMBER($O38)),OFFSET(RiskMatrixRef,-$O38+1,S38-1),"") -> Med | X38: 1) Design procedures to significantly reduce the liklihood of service vessel damaging WEC 2) The probability of occurrence is to be verified against procedures for service vessel. | Y38: See also comment on "improper design" (0111-1) Action the same as "Leak in FRP - fatigue crack due to improper design" for Nacelle Tube | AG38: =IF(AND(ISNUMBER(AC38),ISNUMBER($AB38)),OFFSET(RiskMatrixRef,-$AB38+1,AC38-1),"") | AH38: =IF(AND(ISNUMBER(AD38),ISNUMBER($AB38)),OFFSET(RiskMatrixRef,-$AB38+1,AD38-1),"") | AI38: =IF(AND(ISNUMBER(AE38),ISNUMBER($AB38)),OFFSET(RiskMatrixRef,-$AB38+1,AE38-1),"") | AJ38: =IF(AND(ISNUMBER(AF38),ISNUMBER($AB38)),OFFSET(RiskMatrixRef,-$AB38+1,AF38-1),"") | AS38: =IF(AND(ISNUMBER(AO38),ISNUMBER($AN38)),OFFSET(RiskMatrixRef,-$AN38+1,AO38-1),"") | AT38: =IF(AND(ISNUMBER(AP38),ISNUMBER($AN38)),OFFSET(RiskMatrixRef,-$AN38+1,AP38-1),"") | AU38: =IF(AND(ISNUMBER(AQ38),ISNUMBER($AN38)),OFFSET(RiskMatrixRef,-$AN38+1,AQ38-1),"") | AV38: =IF(AND(ISNUMBER(AR38),ISNUMBER($AN38)),OFFSET(RiskMatrixRef,-$AN38+1,AR38-1),"")
B39: 141-5 142-5 | C39: Spar - STBD / PORT Upper composite / composite joint and Lower composite / steel joint | D39: Connection between upper spar section and lower spar section | E39: 2 | F39: Loading in wave environment, with large motions Manufacturing process for the steel bolting retension flange Long term marine environment | G39: Structural failure | H39: 1) Deteachment of spar sections 2) Damage to WEC | I39: Extreme wave event loading (Overloading) | J39: Normal | M39: 1) visual inspection | N39: Dyr dock repair | O39: 5 | P39: 1 | Q39: 1 | R39: 7 | S39: 7 | T39: =IF(AND(ISNUMBER(P39),ISNUMBER($O39)),OFFSET(RiskMatrixRef,-$O39+1,P39-1),"") -> Low | U39: =IF(AND(ISNUMBER(Q39),ISNUMBER($O39)),OFFSET(RiskMatrixRef,-$O39+1,Q39-1),"") -> Low | V39: =IF(AND(ISNUMBER(R39),ISNUMBER($O39)),OFFSET(RiskMatrixRef,-$O39+1,R39-1),"") -> Med | W39: =IF(AND(ISNUMBER(S39),ISNUMBER($O39)),OFFSET(RiskMatrixRef,-$O39+1,S39-1),"") -> Med | X39: 1) Load derivation methodology to take into account the uncertainties in the loading due to site characterisation measurements and hydrodynamic modelling. 2) Uncertainty of loading estimates to be reduced by comparison of hydrodynamic behavior in simulation versus tank testing. 3) Design load cases to be defined considering all phases (e.g. operating w/ fault, installation, etc.), and to include investigation of localized loading from e.g. slamming. 4) Derivation of localized loading to be developed, and validated via instrumentation of prototype at-sea deployment. | Y39: See also comment on "improper design" (0111-1) Action the same as "Leak in FRP - fatigue crack due to improper design" for Nacelle Tube
B40: 141-6 142-6 | C40: Spar - STBD / PORT Upper composite / composite joint and Lower composite / steel joint | D40: Connection between upper spar section and lower spar section | E40: 2 | F40: Loading in wave environment, with large motions Manufacturing process for the steel bolting retension flange Long term marine environment | G40: Structural failure | H40: 1) Deteachment of spar sections 2) Damage to WEC | I40: Corrosion (including crevice corrosion) | J40: Normal | M40: 1) visual inspection | N40: Dyr dock repair | O40: 7 | P40: 1 | Q40: 1 | R40: 7 | S40: 7 | T40: =IF(AND(ISNUMBER(P40),ISNUMBER($O40)),OFFSET(RiskMatrixRef,-$O40+1,P40-1),"") -> Low | U40: =IF(AND(ISNUMBER(Q40),ISNUMBER($O40)),OFFSET(RiskMatrixRef,-$O40+1,Q40-1),"") -> Low | V40: =IF(AND(ISNUMBER(R40),ISNUMBER($O40)),OFFSET(RiskMatrixRef,-$O40+1,R40-1),"") -> Med | W40: =IF(AND(ISNUMBER(S40),ISNUMBER($O40)),OFFSET(RiskMatrixRef,-$O40+1,S40-1),"") -> Med | X40: 1) Design to incorporate cathodic protection and coating as appropriate (under subsystem 0645 Marinization and Corrosion, External) 2) Establish inspection plan | Y40: See also comment on "improper design" (0111-1) Action the same as "Leak in FRP - fatigue crack due to improper design" for Nacelle Tube
B41: 141-7 142-7 | C41: Spar - STBD / PORT Upper composite / composite joint and Lower composite / steel joint | D41: Connection between upper spar section and lower spar section | E41: 2 | F41: Loading in wave environment, with large motions Manufacturing process for the steel bolting retension flange Long term marine environment | G41: Cracking | H41: 1) Deteachment of spar sections 2) Damage to WEC | I41: Fatigue crack due to uncertainties in loading | J41: Normal | M41: 1) visual inspection | N41: Dyr dock repair | O41: 7 | P41: 1 | Q41: 1 | R41: 7 | S41: 7 | T41: =IF(AND(ISNUMBER(P41),ISNUMBER($O41)),OFFSET(RiskMatrixRef,-$O41+1,P41-1),"") -> Low | U41: =IF(AND(ISNUMBER(Q41),ISNUMBER($O41)),OFFSET(RiskMatrixRef,-$O41+1,Q41-1),"") -> Low | V41: =IF(AND(ISNUMBER(R41),ISNUMBER($O41)),OFFSET(RiskMatrixRef,-$O41+1,R41-1),"") -> Med | W41: =IF(AND(ISNUMBER(S41),ISNUMBER($O41)),OFFSET(RiskMatrixRef,-$O41+1,S41-1),"") -> Med | X41: 1) Load derivation methodology to take into account the uncertainties in the loading due to site characterisation measurements and hydrodynamic modelling. 2) Uncertainty of loading estimates to be reduced by comparison of hydrodynamic behavior in simulation versus tank testing. 3) Design load cases to be defined considering all phases (e.g. operating w/ fault, installation, etc.), and to include investigation of localized loading from e.g. slamming. 4) Derivation of localized loading to be developed, and validated via instrumentation of prototype at-sea deployment. 5) Design fatigue factors (DFF) shall be applied to reduce probability of fatigue failure. 6) Establish inspection plan | Y41: See also comment on "improper design" (0111-1) Action the same as "Leak in FRP - fatigue crack due to improper design" for Nacelle Tube
B42: 0150-1 | C42: Damper | D42: Inertial/drag reaction Wave activated body Provision of watertight compartment | E42: 2 | F42: Loading in wave environment, with large motions | G42: Hole in single comparment | H42: Crack/hole in hull (No water ingress/egress) | I42: Leak in FRP (e.g. manufacturing flaw, assembly) not boat strikes | J42: Normal | K42: 1) vacuum test all water tight compartments 2) V&V for manufacturing and assembly | M42: No detection | N42: No repair necessary | O42: 4 | P42: 1 | Q42: 1 | R42: 1 | S42: 1 | T42: =IF(AND(ISNUMBER(P42),ISNUMBER($O42)),OFFSET(RiskMatrixRef,-$O42+1,P42-1),"") -> Low | U42: =IF(AND(ISNUMBER(Q42),ISNUMBER($O42)),OFFSET(RiskMatrixRef,-$O42+1,Q42-1),"") -> Low | V42: =IF(AND(ISNUMBER(R42),ISNUMBER($O42)),OFFSET(RiskMatrixRef,-$O42+1,R42-1),"") -> Low | W42: =IF(AND(ISNUMBER(S42),ISNUMBER($O42)),OFFSET(RiskMatrixRef,-$O42+1,S42-1),"") -> Low | X42: 1) V&V procedures to be defined and followed, which shall mitigate risk of defective component up to commissioning. | Y42: See also comment on "improper design" (0111-1) Action the same as "Leak in FRP - fatigue crack due to improper design" for Nacelle Tube | AG42: =IF(AND(ISNUMBER(AC42),ISNUMBER($AB42)),OFFSET(RiskMatrixRef,-$AB42+1,AC42-1),"") | AH42: =IF(AND(ISNUMBER(AD42),ISNUMBER($AB42)),OFFSET(RiskMatrixRef,-$AB42+1,AD42-1),"") | AI42: =IF(AND(ISNUMBER(AE42),ISNUMBER($AB42)),OFFSET(RiskMatrixRef,-$AB42+1,AE42-1),"") | AJ42: =IF(AND(ISNUMBER(AF42),ISNUMBER($AB42)),OFFSET(RiskMatrixRef,-$AB42+1,AF42-1),"") | AS42: =IF(AND(ISNUMBER(AO42),ISNUMBER($AN42)),OFFSET(RiskMatrixRef,-$AN42+1,AO42-1),"") | AT42: =IF(AND(ISNUMBER(AP42),ISNUMBER($AN42)),OFFSET(RiskMatrixRef,-$AN42+1,AP42-1),"") | AU42: =IF(AND(ISNUMBER(AQ42),ISNUMBER($AN42)),OFFSET(RiskMatrixRef,-$AN42+1,AQ42-1),"") | AV42: =IF(AND(ISNUMBER(AR42),ISNUMBER($AN42)),OFFSET(RiskMatrixRef,-$AN42+1,AR42-1),"")
B43: 0150-2 | C43: Damper | D43: Inertial/drag reaction Wave activated body Provision of watertight compartment | E43: 2 | F43: Loading in wave environment, with large motions | G43: Hole in single comparment | H43: Crack/hole in hull (No water ingress/egress) | I43: Leak in FRP - fatigue crack due to uncertainties in loading | J43: Normal | K43: 1) All ballast water below waterline | M43: No detection | N43: No repair necessary | O43: 7 | P43: 1 | Q43: 1 | R43: 1 | S43: 1 | T43: =IF(AND(ISNUMBER(P43),ISNUMBER($O43)),OFFSET(RiskMatrixRef,-$O43+1,P43-1),"") -> Low | U43: =IF(AND(ISNUMBER(Q43),ISNUMBER($O43)),OFFSET(RiskMatrixRef,-$O43+1,Q43-1),"") -> Low | V43: =IF(AND(ISNUMBER(R43),ISNUMBER($O43)),OFFSET(RiskMatrixRef,-$O43+1,R43-1),"") -> Low | W43: =IF(AND(ISNUMBER(S43),ISNUMBER($O43)),OFFSET(RiskMatrixRef,-$O43+1,S43-1),"") -> Low | X43: 1) Load derivation methodology to take into account the uncertainties in the loading due to site characterisation measurements and hydrodynamic modelling. 2) Uncertainty of loading estimates to be reduced by comparison of hydrodynamic behavior in simulation versus tank testing. 3) Design load cases to be defined considering all phases (e.g. operating w/ fault, installation, etc.), and to include investigation of localized loading from e.g. slamming. 4) Derivation of localized loading to be developed, and validated via instrumentation of prototype at-sea deployment. 5) Design fatigue factors (DFF) shall be applied to reduce probability of fatigue failure. 6) Establish inspection plan | Y43: See also comment on "improper design" (0111-1) Action the same as "Leak in FRP - fatigue crack due to improper design" for Nacelle Tube | AG43: =IF(AND(ISNUMBER(AC43),ISNUMBER($AB43)),OFFSET(RiskMatrixRef,-$AB43+1,AC43-1),"") | AH43: =IF(AND(ISNUMBER(AD43),ISNUMBER($AB43)),OFFSET(RiskMatrixRef,-$AB43+1,AD43-1),"") | AI43: =IF(AND(ISNUMBER(AE43),ISNUMBER($AB43)),OFFSET(RiskMatrixRef,-$AB43+1,AE43-1),"") | AJ43: =IF(AND(ISNUMBER(AF43),ISNUMBER($AB43)),OFFSET(RiskMatrixRef,-$AB43+1,AF43-1),"") | AS43: =IF(AND(ISNUMBER(AO43),ISNUMBER($AN43)),OFFSET(RiskMatrixRef,-$AN43+1,AO43-1),"") | AT43: =IF(AND(ISNUMBER(AP43),ISNUMBER($AN43)),OFFSET(RiskMatrixRef,-$AN43+1,AP43-1),"") | AU43: =IF(AND(ISNUMBER(AQ43),ISNUMBER($AN43)),OFFSET(RiskMatrixRef,-$AN43+1,AQ43-1),"") | AV43: =IF(AND(ISNUMBER(AR43),ISNUMBER($AN43)),OFFSET(RiskMatrixRef,-$AN43+1,AR43-1),"")
B44: 0150-3 | C44: Damper/Mooring lug connection | D44: Load transfer between mooring lines and WEC hull | E44: 2 | F44: Loading in wave environment, with large motions Bonding between FRP and steel for highly loaded application | G44: Breakage of connection (FRP break) | H44: 1. Loss of mooring connection, hence position keeping 2. Significant greater watch circle 3. Loss of umbillical. | I44: Extreme wave event loading (Overloading) | J44: Normal | K44: none | M44: 1) GPS position alarm 2) Visual detection 3) loss of umibilical connectivity 4) mooring load cell signal | N44: Dry dock repair | O44: 5 | P44: 1 | Q44: 1 | R44: 7 | S44: 7 | T44: =IF(AND(ISNUMBER(P44),ISNUMBER($O44)),OFFSET(RiskMatrixRef,-$O44+1,P44-1),"") -> Low | U44: =IF(AND(ISNUMBER(Q44),ISNUMBER($O44)),OFFSET(RiskMatrixRef,-$O44+1,Q44-1),"") -> Low | V44: =IF(AND(ISNUMBER(R44),ISNUMBER($O44)),OFFSET(RiskMatrixRef,-$O44+1,R44-1),"") -> Med | W44: =IF(AND(ISNUMBER(S44),ISNUMBER($O44)),OFFSET(RiskMatrixRef,-$O44+1,S44-1),"") -> Med | X44: 1) Load derivation methodology to take into account the uncertainties in the loading due to site characterisation measurements and hydrodynamic modelling. 2) Uncertainty of loading estimates to be reduced by comparison of hydrodynamic behavior in simulation versus tank testing. 3) Design load cases to be defined considering all phases (e.g. operating w/ fault, installation, etc.), and to include investigation of localized loading from e.g. slamming. 4) Derivation of localized loading to be developed, and validated via instrumentation of prototype at-sea deployment. 5) Design to demonstrate that the mooring lines are to break first in the event of excessive loading in order to prevent any damage to the connection points on the WEC hull area such that dry dock repair is not necessary in the event of line failure 6) Bonding of the steel and FRP to be qualified, via component testing to design load | Y44: Suggest text for recommended action: Bonding of the steel and FRP to be qualified, via component testing to design load validate the model and demonstrate the integrity of the interface. Action in "Extreme wave event loading" for hull applicable
B45: 0150-4 | C45: Damper/Mooring lug connection | D45: Load transfer between mooring lines and WEC hull | E45: 2 | F45: Loading in wave environment, with large motions Bonding between FRP and steel for highly loaded application | G45: Breakage of connection (FRP break) | H45: 1. Loss of mooring connection, hence position keeping 2. Significant greater watch circle 3. Loss of umbillical. | I45: Fatigue | J45: Normal | K45: none | M45: 1) GPS position alarm 2) Visual detection 3) loss of umibilical connectivity 4) mooring load cell signal | N45: Dry dock repair | O45: 7 | P45: 1 | Q45: 1 | R45: 7 | S45: 7 | T45: =IF(AND(ISNUMBER(P45),ISNUMBER($O45)),OFFSET(RiskMatrixRef,-$O45+1,P45-1),"") -> Low | U45: =IF(AND(ISNUMBER(Q45),ISNUMBER($O45)),OFFSET(RiskMatrixRef,-$O45+1,Q45-1),"") -> Low | V45: =IF(AND(ISNUMBER(R45),ISNUMBER($O45)),OFFSET(RiskMatrixRef,-$O45+1,R45-1),"") -> Med | W45: =IF(AND(ISNUMBER(S45),ISNUMBER($O45)),OFFSET(RiskMatrixRef,-$O45+1,S45-1),"") -> Med | X45: 1) Load derivation methodology to take into account the uncertainties in the loading due to site characterisation measurements and hydrodynamic modelling. 2) Uncertainty of loading estimates to be reduced by comparison of hydrodynamic behavior in simulation versus tank testing. 3) Design load cases to be defined considering all phases (e.g. operating w/ fault, installation, etc.), and to include investigation of localized loading from e.g. slamming. 4) Derivation of localized loading to be developed, and validated via instrumentation of prototype at-sea deployment. 5) Design fatigue factors (DFF) shall be applied to reduce probability of fatigue failure. 6) Establish inspection plan | Y45: Suggest text for recommended action: Bonding of the steel and FRP to be qualified, via component testing to design load validate the model and demonstrate the integrity of the interface. Action in "Fatigue and other degradation mechanisms" for hull applicable | AG45: =IF(AND(ISNUMBER(AC45),ISNUMBER($AB45)),OFFSET(RiskMatrixRef,-$AB45+1,AC45-1),"") | AH45: =IF(AND(ISNUMBER(AD45),ISNUMBER($AB45)),OFFSET(RiskMatrixRef,-$AB45+1,AD45-1),"") | AI45: =IF(AND(ISNUMBER(AE45),ISNUMBER($AB45)),OFFSET(RiskMatrixRef,-$AB45+1,AE45-1),"") | AJ45: =IF(AND(ISNUMBER(AF45),ISNUMBER($AB45)),OFFSET(RiskMatrixRef,-$AB45+1,AF45-1),"") | AS45: =IF(AND(ISNUMBER(AO45),ISNUMBER($AN45)),OFFSET(RiskMatrixRef,-$AN45+1,AO45-1),"") | AT45: =IF(AND(ISNUMBER(AP45),ISNUMBER($AN45)),OFFSET(RiskMatrixRef,-$AN45+1,AP45-1),"") | AU45: =IF(AND(ISNUMBER(AQ45),ISNUMBER($AN45)),OFFSET(RiskMatrixRef,-$AN45+1,AQ45-1),"") | AV45: =IF(AND(ISNUMBER(AR45),ISNUMBER($AN45)),OFFSET(RiskMatrixRef,-$AN45+1,AR45-1),"")
B46: 0100-3 | C46: HAT stiffners | D46: Provide additional stiffness to the floats, nacelle and damper | E46: 2 | F46: Laminating and bonding process of the stiffners | G46: Delamination | H46: 1. Reduction in stiffness of the component 2. Excessive deformation of the component leading to increase in probability of occurrence of other failure mode, for instance reduction in air gap or sea leakage due to deformation of floats | I46: Extreme wave event loading (Overloading) | J46: Normal | K46: none | M46: 1) visual inspection | N46: Dry dock repair | O46: 4 | P46: 1 | Q46: 1 | R46: 7 | S46: 7 | T46: =IF(AND(ISNUMBER(P46),ISNUMBER($O46)),OFFSET(RiskMatrixRef,-$O46+1,P46-1),"") -> Low | U46: =IF(AND(ISNUMBER(Q46),ISNUMBER($O46)),OFFSET(RiskMatrixRef,-$O46+1,Q46-1),"") -> Low | V46: =IF(AND(ISNUMBER(R46),ISNUMBER($O46)),OFFSET(RiskMatrixRef,-$O46+1,R46-1),"") -> Low | W46: =IF(AND(ISNUMBER(S46),ISNUMBER($O46)),OFFSET(RiskMatrixRef,-$O46+1,S46-1),"") -> Low | X46: none | Y46: High severity class assumed because worst failure assumed, but lower occurrence class assigned. | AG46: =IF(AND(ISNUMBER(AC46),ISNUMBER($AB46)),OFFSET(RiskMatrixRef,-$AB46+1,AC46-1),"") | AH46: =IF(AND(ISNUMBER(AD46),ISNUMBER($AB46)),OFFSET(RiskMatrixRef,-$AB46+1,AD46-1),"") | AI46: =IF(AND(ISNUMBER(AE46),ISNUMBER($AB46)),OFFSET(RiskMatrixRef,-$AB46+1,AE46-1),"") | AJ46: =IF(AND(ISNUMBER(AF46),ISNUMBER($AB46)),OFFSET(RiskMatrixRef,-$AB46+1,AF46-1),"") | AS46: =IF(AND(ISNUMBER(AO46),ISNUMBER($AN46)),OFFSET(RiskMatrixRef,-$AN46+1,AO46-1),"") | AT46: =IF(AND(ISNUMBER(AP46),ISNUMBER($AN46)),OFFSET(RiskMatrixRef,-$AN46+1,AP46-1),"") | AU46: =IF(AND(ISNUMBER(AQ46),ISNUMBER($AN46)),OFFSET(RiskMatrixRef,-$AN46+1,AQ46-1),"") | AV46: =IF(AND(ISNUMBER(AR46),ISNUMBER($AN46)),OFFSET(RiskMatrixRef,-$AN46+1,AR46-1),"")
B47: 0100-4 | C47: HAT stiffners | D47: Provide additional stiffness to the floats, nacelle and damper | E47: 2 | F47: Laminating and bonding process of the stiffners | G47: Delamination | H47: 1. Reduction in stiffness of the component 2. Excessive deformation of the component leading to increase in probability of occurrence of other failure mode, for instance reduction in air gap or sea leakage due to deformation of floats | I47: Fatigue | J47: Normal | K47: none | M47: 1) visual inspection | N47: Dry dock repair | O47: 6 | P47: 1 | Q47: 1 | R47: 7 | S47: 7 | T47: =IF(AND(ISNUMBER(P47),ISNUMBER($O47)),OFFSET(RiskMatrixRef,-$O47+1,P47-1),"") -> Low | U47: =IF(AND(ISNUMBER(Q47),ISNUMBER($O47)),OFFSET(RiskMatrixRef,-$O47+1,Q47-1),"") -> Low | V47: =IF(AND(ISNUMBER(R47),ISNUMBER($O47)),OFFSET(RiskMatrixRef,-$O47+1,R47-1),"") -> Med | W47: =IF(AND(ISNUMBER(S47),ISNUMBER($O47)),OFFSET(RiskMatrixRef,-$O47+1,S47-1),"") -> Med | X47: 1) Load derivation methodology to take into account the uncertainties in the loading due to site characterisation measurements and hydrodynamic modelling. 2) Uncertainty of loading estimates to be reduced by comparison of hydrodynamic behavior in simulation versus tank testing. 3) Design load cases to be defined considering all phases (e.g. operating w/ fault, installation, etc.), and to include investigation of localized loading from e.g. slamming. 4) Derivation of localized loading to be developed, and validated via instrumentation of prototype at-sea deployment. 5) Design fatigue factors (DFF) shall be applied to reduce probability of fatigue failure. 6) Establish inspection plan | Y47: High severity class assumed because worst failure assumed, but lower occurrence class assigned. Suggest text for recommended action: Bonding of the steel and FRP to be qualified, via component testing to design load validate the model and demonstrate the integrity of the interface. Action in "Fatigue and other degradation mechanisms" for hull applicable | AG47: =IF(AND(ISNUMBER(AC47),ISNUMBER($AB47)),OFFSET(RiskMatrixRef,-$AB47+1,AC47-1),"") | AH47: =IF(AND(ISNUMBER(AD47),ISNUMBER($AB47)),OFFSET(RiskMatrixRef,-$AB47+1,AD47-1),"") | AI47: =IF(AND(ISNUMBER(AE47),ISNUMBER($AB47)),OFFSET(RiskMatrixRef,-$AB47+1,AE47-1),"") | AJ47: =IF(AND(ISNUMBER(AF47),ISNUMBER($AB47)),OFFSET(RiskMatrixRef,-$AB47+1,AF47-1),"") | AS47: =IF(AND(ISNUMBER(AO47),ISNUMBER($AN47)),OFFSET(RiskMatrixRef,-$AN47+1,AO47-1),"") | AT47: =IF(AND(ISNUMBER(AP47),ISNUMBER($AN47)),OFFSET(RiskMatrixRef,-$AN47+1,AP47-1),"") | AU47: =IF(AND(ISNUMBER(AQ47),ISNUMBER($AN47)),OFFSET(RiskMatrixRef,-$AN47+1,AQ47-1),"") | AV47: =IF(AND(ISNUMBER(AR47),ISNUMBER($AN47)),OFFSET(RiskMatrixRef,-$AN47+1,AR47-1),"")

Sheet version history
A1: Title | B1: StingRAY Hull Structrure FMECA
A2: Doc No | B2: SR-0100-RR
A3: Version | B3: 3.0
A4: Authored | B4: E Hammagren
A5: CPwr Review | B5: P Lenee-Bluhm, J Prudell, A Schacher, Z Zhang, M Ondusko
A6: Expert Review
A7: Eng man Appr
A8: Corp Appr
A11: Version | B11: Date | C11: Summary
A12: 1.0 | B12: 41673 | C12: Released to GH for review
A13: 1.1 | B13: 41716 | C13: Edits following GH review
A14: 2.0 | B14: 41968 | C14: New format and risk ranking, additional input
A15: 2.1 | B15: 42398 | C15: Major revision following DNVGL RC review
A16: 3.0 | B16: 42576 | C16: Updated risk matrix, updated for WEC v3.3 technology
A23: The following contains PROTECTED DATA of Columbia Power Technologies, Inc. not for distribution.

Sheet set up
C2: =linkedPage!C2 -> Risk = Occ + Sev | O2: =linkedPage!T2 -> Note:
C3: =linkedPage!C3 -> Severity | O3: =linkedPage!T3 -> - 'set up' and 'linkedPage' are both linked to workbook 'FMECA Master v3.xlsx'
B4: =IF(linkedPage!B4=0,"",linkedPage!B4) -> Occ | C4: =IF(linkedPage!C4=0,"",linkedPage!C4) -> 1 | D4: =IF(linkedPage!D4=0,"",linkedPage!D4) -> 2 | E4: =IF(linkedPage!E4=0,"",linkedPage!E4) -> 3 | F4: =IF(linkedPage!F4=0,"",linkedPage!F4) -> 4 | G4: =IF(linkedPage!G4=0,"",linkedPage!G4) -> 5 | H4: =IF(linkedPage!H4=0,"",linkedPage!H4) -> 6 | I4: =IF(linkedPage!I4=0,"",linkedPage!I4) -> 7 | ... N4: =IF(linkedPage!N4=0,"",linkedPage!N4) | O4: =linkedPage!T4 -> - changes to the tables, risk scores, etc must be made in 'FMECA Master v3.xlsx'
B5: =IF(linkedPage!B5=0,"",linkedPage!B5) -> 10 | C5: =IF(linkedPage!C5=0,"",linkedPage!C5) -> Low | D5: =IF(linkedPage!D5=0,"",linkedPage!D5) -> Med | E5: =IF(linkedPage!E5=0,"",linkedPage!E5) -> Med | F5: =IF(linkedPage!F5=0,"",linkedPage!F5) -> Med | G5: =IF(linkedPage!G5=0,"",linkedPage!G5) -> Med | H5: =IF(linkedPage!H5=0,"",linkedPage!H5) -> High | I5: =IF(linkedPage!I5=0,"",linkedPage!I5) -> High | ... O5: =IF(linkedPage!O5=0,"",linkedPage!O5)
B6: =IF(linkedPage!B6=0,"",linkedPage!B6) -> 9 | C6: =IF(linkedPage!C6=0,"",linkedPage!C6) -> Low | D6: =IF(linkedPage!D6=0,"",linkedPage!D6) -> Low | E6: =IF(linkedPage!E6=0,"",linkedPage!E6) -> Med | F6: =IF(linkedPage!F6=0,"",linkedPage!F6) -> Med | G6: =IF(linkedPage!G6=0,"",linkedPage!G6) -> Med | H6: =IF(linkedPage!H6=0,"",linkedPage!H6) -> Med | I6: =IF(linkedPage!I6=0,"",linkedPage!I6) -> High | ... O6: =IF(linkedPage!O6=0,"",linkedPage!O6)
B7: =IF(linkedPage!B7=0,"",linkedPage!B7) -> 8 | C7: =IF(linkedPage!C7=0,"",linkedPage!C7) -> Low | D7: =IF(linkedPage!D7=0,"",linkedPage!D7) -> Low | E7: =IF(linkedPage!E7=0,"",linkedPage!E7) -> Low | F7: =IF(linkedPage!F7=0,"",linkedPage!F7) -> Med | G7: =IF(linkedPage!G7=0,"",linkedPage!G7) -> Med | H7: =IF(linkedPage!H7=0,"",linkedPage!H7) -> Med | I7: =IF(linkedPage!I7=0,"",linkedPage!I7) -> Med | ... O7: =IF(linkedPage!O7=0,"",linkedPage!O7)
B8: =IF(linkedPage!B8=0,"",linkedPage!B8) -> 7 | C8: =IF(linkedPage!C8=0,"",linkedPage!C8) -> Low | D8: =IF(linkedPage!D8=0,"",linkedPage!D8) -> Low | E8: =IF(linkedPage!E8=0,"",linkedPage!E8) -> Low | F8: =IF(linkedPage!F8=0,"",linkedPage!F8) -> Low | G8: =IF(linkedPage!G8=0,"",linkedPage!G8) -> Med | H8: =IF(linkedPage!H8=0,"",linkedPage!H8) -> Med | I8: =IF(linkedPage!I8=0,"",linkedPage!I8) -> Med | ... O8: =IF(linkedPage!O8=0,"",linkedPage!O8)
B9: =IF(linkedPage!B9=0,"",linkedPage!B9) -> 6 | C9: =IF(linkedPage!C9=0,"",linkedPage!C9) -> Low | D9: =IF(linkedPage!D9=0,"",linkedPage!D9) -> Low | E9: =IF(linkedPage!E9=0,"",linkedPage!E9) -> Low | F9: =IF(linkedPage!F9=0,"",linkedPage!F9) -> Low | G9: =IF(linkedPage!G9=0,"",linkedPage!G9) -> Low | H9: =IF(linkedPage!H9=0,"",linkedPage!H9) -> Med | I9: =IF(linkedPage!I9=0,"",linkedPage!I9) -> Med | ... O9: =IF(linkedPage!O9=0,"",linkedPage!O9)
B10: =IF(linkedPage!B10=0,"",linkedPage!B10) -> 5 | C10: =IF(linkedPage!C10=0,"",linkedPage!C10) -> Low | D10: =IF(linkedPage!D10=0,"",linkedPage!D10) -> Low | E10: =IF(linkedPage!E10=0,"",linkedPage!E10) -> Low | F10: =IF(linkedPage!F10=0,"",linkedPage!F10) -> Low | G10: =IF(linkedPage!G10=0,"",linkedPage!G10) -> Low | H10: =IF(linkedPage!H10=0,"",linkedPage!H10) -> Low | I10: =IF(linkedPage!I10=0,"",linkedPage!I10) -> Med | ... O10: =IF(linkedPage!O10=0,"",linkedPage!O10)
B11: =IF(linkedPage!B11=0,"",linkedPage!B11) -> 4 | C11: =IF(linkedPage!C11=0,"",linkedPage!C11) -> Low | D11: =IF(linkedPage!D11=0,"",linkedPage!D11) -> Low | E11: =IF(linkedPage!E11=0,"",linkedPage!E11) -> Low | F11: =IF(linkedPage!F11=0,"",linkedPage!F11) -> Low | G11: =IF(linkedPage!G11=0,"",linkedPage!G11) -> Low | H11: =IF(linkedPage!H11=0,"",linkedPage!H11) -> Low | I11: =IF(linkedPage!I11=0,"",linkedPage!I11) -> Low | ... O11: =IF(linkedPage!O11=0,"",linkedPage!O11) -> Tolerable, no engineer action required
B12: =IF(linkedPage!B12=0,"",linkedPage!B12) -> 3 | C12: =IF(linkedPage!C12=0,"",linkedPage!C12) -> Low | D12: =IF(linkedPage!D12=0,"",linkedPage!D12) -> Low | E12: =IF(linkedPage!E12=0,"",linkedPage!E12) -> Low | F12: =IF(linkedPage!F12=0,"",linkedPage!F12) -> Low | G12: =IF(linkedPage!G12=0,"",linkedPage!G12) -> Low | H12: =IF(linkedPage!H12=0,"",linkedPage!H12) -> Low | I12: =IF(linkedPage!I12=0,"",linkedPage!I12) -> Low | ... O12: =IF(linkedPage!O12=0,"",linkedPage!O12) -> Undesirable, consider engineer actions to mitigate risk
B13: =IF(linkedPage!B13=0,"",linkedPage!B13) -> 2 | C13: =IF(linkedPage!C13=0,"",linkedPage!C13) -> Low | D13: =IF(linkedPage!D13=0,"",linkedPage!D13) -> Low | E13: =IF(linkedPage!E13=0,"",linkedPage!E13) -> Low | F13: =IF(linkedPage!F13=0,"",linkedPage!F13) -> Low | G13: =IF(linkedPage!G13=0,"",linkedPage!G13) -> Low | H13: =IF(linkedPage!H13=0,"",linkedPage!H13) -> Low | I13: =IF(linkedPage!I13=0,"",linkedPage!I13) -> Low | ... O13: =IF(linkedPage!O13=0,"",linkedPage!O13) -> Intolerable, engineering action required
B14: =IF(linkedPage!B14=0,"",linkedPage!B14) -> 1 | C14: =IF(linkedPage!C14=0,"",linkedPage!C14) -> Low | D14: =IF(linkedPage!D14=0,"",linkedPage!D14) -> Low | E14: =IF(linkedPage!E14=0,"",linkedPage!E14) -> Low | F14: =IF(linkedPage!F14=0,"",linkedPage!F14) -> Low | G14: =IF(linkedPage!G14=0,"",linkedPage!G14) -> Low | H14: =IF(linkedPage!H14=0,"",linkedPage!H14) -> Low | I14: =IF(linkedPage!I14=0,"",linkedPage!I14) -> Low | ... O14: =IF(linkedPage!O14=0,"",linkedPage!O14)
B16: =IF(linkedPage!B16=0,"",linkedPage!B16) -> Occurrence | H16: =IF(linkedPage!H16=0,"",linkedPage!H16) -> Severity
B17: =IF(linkedPage!B17=0,"",linkedPage!B17) -> Rating | C17: =IF(linkedPage!C17=0,"",linkedPage!C17) -> Occurrence | D17: =IF(linkedPage!D17=0,"",linkedPage!D17) | E17: =IF(linkedPage!E17=0,"",linkedPage!E17) -> Annual Failure Rate | F17: =IF(linkedPage!F17=0,"",linkedPage!F17) -> Return Period [years] | H17: =IF(linkedPage!H17=0,"",linkedPage!H17) -> Rating | I17: =IF(linkedPage!I17=0,"",linkedPage!I17) -> Severity | J17: =IF(linkedPage!J17=0,"",linkedPage!J17) -> Human Safety | K17: =IF(linkedPage!K17=0,"",linkedPage!K17) | L17: =IF(linkedPage!L17=0,"",linkedPage!L17) -> Environment | M17: =IF(linkedPage!M17=0,"",linkedPage!M17) | N17: =IF(linkedPage!N17=0,"",linkedPage!N17) -> WEC Operation | O17: =IF(linkedPage!O17=0,"",linkedPage!O17) | ... Q17: =IF(linkedPage!Q17=0,"",linkedPage!Q17)
B18: =IF(linkedPage!B18=0,"",linkedPage!B18) -> 1 | C18: =IF(linkedPage!C18=0,"",linkedPage!C18) -> Exceptionally unlikely to occur | D18: =IF(linkedPage!D18=0,"",linkedPage!D18) | E18: =IF(linkedPage!E18=0,"",linkedPage!E18) -> 1e-05 | F18: =IF(linkedPage!F18=0,"",linkedPage!F18) -> 100000 | H18: =IF(linkedPage!H18=0,"",linkedPage!H18) -> 1 | I18: =IF(linkedPage!I18=0,"",linkedPage!I18) -> Insignificant | J18: =IF(linkedPage!J18=0,"",linkedPage!J18) -> Negligible injury, effect on health (e.g. band aid) | K18: =IF(linkedPage!K18=0,"",linkedPage!K18) | L18: =IF(linkedPage!L18=0,"",linkedPage!L18) -> Negligible pollution or no effect on environment | M18: =IF(linkedPage!M18=0,"",linkedPage!M18) | N18: =IF(linkedPage!N18=0,"",linkedPage!N18) -> Negligible effect on performance | O18: =IF(linkedPage!O18=0,"",linkedPage!O18) | ... Q18: =IF(linkedPage!Q18=0,"",linkedPage!Q18)
B19: =IF(linkedPage!B19=0,"",linkedPage!B19) -> 2 | C19: =IF(linkedPage!C19=0,"",linkedPage!C19) | D19: =IF(linkedPage!D19=0,"",linkedPage!D19) | E19: =IF(linkedPage!E19=0,"",linkedPage!E19) -> 3.1622777e-05 | F19: =IF(linkedPage!F19=0,"",linkedPage!F19) -> 31600 | H19: =IF(linkedPage!H19=0,"",linkedPage!H19) -> 2 | I19: =IF(linkedPage!I19=0,"",linkedPage!I19) | J19: =IF(linkedPage!J19=0,"",linkedPage!J19) | K19: =IF(linkedPage!K19=0,"",linkedPage!K19) | L19: =IF(linkedPage!L19=0,"",linkedPage!L19) | M19: =IF(linkedPage!M19=0,"",linkedPage!M19) | N19: =IF(linkedPage!N19=0,"",linkedPage!N19) | O19: =IF(linkedPage!O19=0,"",linkedPage!O19) | ... Q19: =IF(linkedPage!Q19=0,"",linkedPage!Q19)
B20: =IF(linkedPage!B20=0,"",linkedPage!B20) -> 3 | C20: =IF(linkedPage!C20=0,"",linkedPage!C20) -> Extremely unlikely to occur | D20: =IF(linkedPage!D20=0,"",linkedPage!D20) | E20: =IF(linkedPage!E20=0,"",linkedPage!E20) -> 0.0001 | F20: =IF(linkedPage!F20=0,"",linkedPage!F20) -> 10000 | H20: =IF(linkedPage!H20=0,"",linkedPage!H20) -> 3 | I20: =IF(linkedPage!I20=0,"",linkedPage!I20) -> Minor | J20: =IF(linkedPage!J20=0,"",linkedPage!J20) -> Minor injuries, health effects (e.g. stitches) | K20: =IF(linkedPage!K20=0,"",linkedPage!K20) | L20: =IF(linkedPage!L20=0,"",linkedPage!L20) -> Minor pollution / slight effect on environment (min disruption on marine life) | M20: =IF(linkedPage!M20=0,"",linkedPage!M20) | N20: =IF(linkedPage!N20=0,"",linkedPage!N20) -> Minor system degradation | O20: =IF(linkedPage!O20=0,"",linkedPage!O20) | ... Q20: =IF(linkedPage!Q20=0,"",linkedPage!Q20)
B21: =IF(linkedPage!B21=0,"",linkedPage!B21) -> 4 | C21: =IF(linkedPage!C21=0,"",linkedPage!C21) | D21: =IF(linkedPage!D21=0,"",linkedPage!D21) | E21: =IF(linkedPage!E21=0,"",linkedPage!E21) -> 0.00031622777 | F21: =IF(linkedPage!F21=0,"",linkedPage!F21) -> 3160 | H21: =IF(linkedPage!H21=0,"",linkedPage!H21) -> 4 | I21: =IF(linkedPage!I21=0,"",linkedPage!I21) | J21: =IF(linkedPage!J21=0,"",linkedPage!J21) -> Moderate injuries and/or health effects (e.g. broken bone) | K21: =IF(linkedPage!K21=0,"",linkedPage!K21) | L21: =IF(linkedPage!L21=0,"",linkedPage!L21) | M21: =IF(linkedPage!M21=0,"",linkedPage!M21) | N21: =IF(linkedPage!N21=0,"",linkedPage!N21) -> Moderate system degradation (e.g. loss of MoMo) | O21: =IF(linkedPage!O21=0,"",linkedPage!O21) | ... Q21: =IF(linkedPage!Q21=0,"",linkedPage!Q21)
B22: =IF(linkedPage!B22=0,"",linkedPage!B22) -> 5 | C22: =IF(linkedPage!C22=0,"",linkedPage!C22) -> Very unlikely to occur | D22: =IF(linkedPage!D22=0,"",linkedPage!D22) | E22: =IF(linkedPage!E22=0,"",linkedPage!E22) -> 0.001 | F22: =IF(linkedPage!F22=0,"",linkedPage!F22) -> 1000 | H22: =IF(linkedPage!H22=0,"",linkedPage!H22) -> 5 | I22: =IF(linkedPage!I22=0,"",linkedPage!I22) -> Major | J22: =IF(linkedPage!J22=0,"",linkedPage!J22) | K22: =IF(linkedPage!K22=0,"",linkedPage!K22) | L22: =IF(linkedPage!L22=0,"",linkedPage!L22) -> Limited levels of pollution, manageable / moderate effect on environment | M22: =IF(linkedPage!M22=0,"",linkedPage!M22) | N22: =IF(linkedPage!N22=0,"",linkedPage!N22) | O22: =IF(linkedPage!O22=0,"",linkedPage!O22) | ... Q22: =IF(linkedPage!Q22=0,"",linkedPage!Q22)
B23: =IF(linkedPage!B23=0,"",linkedPage!B23) -> 6 | C23: =IF(linkedPage!C23=0,"",linkedPage!C23) | D23: =IF(linkedPage!D23=0,"",linkedPage!D23) | E23: =IF(linkedPage!E23=0,"",linkedPage!E23) -> 0.0031622777 | F23: =IF(linkedPage!F23=0,"",linkedPage!F23) -> 316 | H23: =IF(linkedPage!H23=0,"",linkedPage!H23) -> 6 | I23: =IF(linkedPage!I23=0,"",linkedPage!I23) | J23: =IF(linkedPage!J23=0,"",linkedPage!J23) | K23: =IF(linkedPage!K23=0,"",linkedPage!K23) | L23: =IF(linkedPage!L23=0,"",linkedPage!L23) | M23: =IF(linkedPage!M23=0,"",linkedPage!M23) | N23: =IF(linkedPage!N23=0,"",linkedPage!N23) -> Major system degradation or loss of operation for 1 month | O23: =IF(linkedPage!O23=0,"",linkedPage!O23) | ... Q23: =IF(linkedPage!Q23=0,"",linkedPage!Q23)
B24: =IF(linkedPage!B24=0,"",linkedPage!B24) -> 7 | C24: =IF(linkedPage!C24=0,"",linkedPage!C24) -> Rarely expected to occur | D24: =IF(linkedPage!D24=0,"",linkedPage!D24) | E24: =IF(linkedPage!E24=0,"",linkedPage!E24) -> 0.01 | F24: =IF(linkedPage!F24=0,"",linkedPage!F24) -> 100 | H24: =IF(linkedPage!H24=0,"",linkedPage!H24) -> 7 | I24: =IF(linkedPage!I24=0,"",linkedPage!I24) -> Critical | J24: =IF(linkedPage!J24=0,"",linkedPage!J24) -> Hospitalization (with full recovery) | K24: =IF(linkedPage!K24=0,"",linkedPage!K24) | L24: =IF(linkedPage!L24=0,"",linkedPage!L24) -> Moderate pollution (some clean-up costs) / Serious effect on environment | M24: =IF(linkedPage!M24=0,"",linkedPage!M24) | N24: =IF(linkedPage!N24=0,"",linkedPage!N24) -> Major system degradation or loss of operation for 3 months | O24: =IF(linkedPage!O24=0,"",linkedPage!O24) | ... Q24: =IF(linkedPage!Q24=0,"",linkedPage!Q24)
B25: =IF(linkedPage!B25=0,"",linkedPage!B25) -> 8 | C25: =IF(linkedPage!C25=0,"",linkedPage!C25) | D25: =IF(linkedPage!D25=0,"",linkedPage!D25) | E25: =IF(linkedPage!E25=0,"",linkedPage!E25) -> 0.031622777 | F25: =IF(linkedPage!F25=0,"",linkedPage!F25) -> 31.6 | H25: =IF(linkedPage!H25=0,"",linkedPage!H25) -> 8 | I25: =IF(linkedPage!I25=0,"",linkedPage!I25) | J25: =IF(linkedPage!J25=0,"",linkedPage!J25) | K25: =IF(linkedPage!K25=0,"",linkedPage!K25) | L25: =IF(linkedPage!L25=0,"",linkedPage!L25) | M25: =IF(linkedPage!M25=0,"",linkedPage!M25) | N25: =IF(linkedPage!N25=0,"",linkedPage!N25) -> Critical system degradation or loss of operation for 6 months | O25: =IF(linkedPage!O25=0,"",linkedPage!O25) | ... Q25: =IF(linkedPage!Q25=0,"",linkedPage!Q25)
B26: =IF(linkedPage!B26=0,"",linkedPage!B26) -> 9 | C26: =IF(linkedPage!C26=0,"",linkedPage!C26) -> One or more during 20 yr lifetime | D26: =IF(linkedPage!D26=0,"",linkedPage!D26) | E26: =IF(linkedPage!E26=0,"",linkedPage!E26) -> 0.1 | F26: =IF(linkedPage!F26=0,"",linkedPage!F26) -> 10 | H26: =IF(linkedPage!H26=0,"",linkedPage!H26) -> 9 | I26: =IF(linkedPage!I26=0,"",linkedPage!I26) -> Catastrophic | J26: =IF(linkedPage!J26=0,"",linkedPage!J26) -> Hospitalization (with lasting disabilities) | K26: =IF(linkedPage!K26=0,"",linkedPage!K26) | L26: =IF(linkedPage!L26=0,"",linkedPage!L26) -> Major pollution (significant clean-up costs) / disastrous effects on the environment | M26: =IF(linkedPage!M26=0,"",linkedPage!M26) | N26: =IF(linkedPage!N26=0,"",linkedPage!N26) -> Failure to generate power for remainder of project, complete failure | O26: =IF(linkedPage!O26=0,"",linkedPage!O26) | ... Q26: =IF(linkedPage!Q26=0,"",linkedPage!Q26)
B27: =IF(linkedPage!B27=0,"",linkedPage!B27) -> 10 | C27: =IF(linkedPage!C27=0,"",linkedPage!C27) | D27: =IF(linkedPage!D27=0,"",linkedPage!D27) | E27: =IF(linkedPage!E27=0,"",linkedPage!E27) -> 0.31622777 | F27: =IF(linkedPage!F27=0,"",linkedPage!F27) -> 3.16 | H27: =IF(linkedPage!H27=0,"",linkedPage!H27) -> 10 | I27: =IF(linkedPage!I27=0,"",linkedPage!I27) | J27: =IF(linkedPage!J27=0,"",linkedPage!J27) -> A fatality | K27: =IF(linkedPage!K27=0,"",linkedPage!K27) | L27: =IF(linkedPage!L27=0,"",linkedPage!L27) | M27: =IF(linkedPage!M27=0,"",linkedPage!M27) | N27: =IF(linkedPage!N27=0,"",linkedPage!N27) | O27: =IF(linkedPage!O27=0,"",linkedPage!O27) | ... Q27: =IF(linkedPage!Q27=0,"",linkedPage!Q27)

Sheet linkedPage
A1: {=[1]!'!set up!R1C1:R27C17'} -> 0 | B1: 0 | C1: 0 | D1: 0 | E1: 0 | F1: 0 | G1: 0 | H1: 0 | I1: 0 | J1: 0 | K1: 0 | L1: 0 | M1: 0 | N1: 0 | O1: 0 | P1: 0 | Q1: 0
A2: 0 | B2: 0 | C2: Risk = Occ + Sev | D2: 0 | E2: 0 | F2: 0 | G2: 0 | H2: 0 | I2: 0 | J2: 0 | K2: 0 | L2: 0 | M2: 0 | N2: 0 | O2: 0 | P2: 0 | Q2: 0 | T2: Note:
A3: 0 | B3: 0 | C3: Severity | D3: 0 | E3: 0 | F3: 0 | G3: 0 | H3: 0 | I3: 0 | J3: 0 | K3: 0 | L3: 0 | M3: 0 | N3: 0 | O3: 0 | P3: 0 | Q3: 0 | T3: - 'set up' and 'linkedPage' are both linked to workbook 'FMECA Master v3.xlsx'
A4: 0 | B4: Occ | C4: 1 | D4: 2 | E4: 3 | F4: 4 | G4: 5 | H4: 6 | I4: 7 | J4: 8 | K4: 9 | L4: 10 | M4: 0 | N4: 0 | O4: 0 | P4: 0 | Q4: 0 | T4: - changes to the tables, risk scores, etc must be made in 'FMECA Master v3.xlsx'
A5: 0 | B5: 10 | C5: Low | D5: Med | E5: Med | F5: Med | G5: Med | H5: High | I5: High | J5: High | K5: High | L5: High | M5: 0 | N5: 0 | O5: 0 | P5: 0 | Q5: 0
A6: 0 | B6: 9 | C6: Low | D6: Low | E6: Med | F6: Med | G6: Med | H6: Med | I6: High | J6: High | K6: High | L6: High | M6: low <= | N6: 11 | O6: 0 | P6: 0 | Q6: 0
A7: 0 | B7: 8 | C7: Low | D7: Low | E7: Low | F7: Med | G7: Med | H7: Med | I7: Med | J7: High | K7: High | L7: High | M7: high> | N7: 15 | O7: 0 | P7: 0 | Q7: 0
A8: 0 | B8: 7 | C8: Low | D8: Low | E8: Low | F8: Low | G8: Med | H8: Med | I8: Med | J8: Med | K8: High | L8: High | M8: 0 | N8: 0 | O8: 0 | P8: 0 | Q8: 0
A9: 0 | B9: 6 | C9: Low | D9: Low | E9: Low | F9: Low | G9: Low | H9: Med | I9: Med | J9: Med | K9: Med | L9: High | M9: 0 | N9: 0 | O9: 0 | P9: 0 | Q9: 0
A10: 0 | B10: 5 | C10: Low | D10: Low | E10: Low | F10: Low | G10: Low | H10: Low | I10: Med | J10: Med | K10: Med | L10: Med | M10: 0 | N10: 0 | O10: 0 | P10: 0 | Q10: 0
A11: 0 | B11: 4 | C11: Low | D11: Low | E11: Low | F11: Low | G11: Low | H11: Low | I11: Low | J11: Med | K11: Med | L11: Med | M11: 0 | N11: Low | O11: Tolerable, no engineer action required | P11: 0 | Q11: 0
A12: 0 | B12: 3 | C12: Low | D12: Low | E12: Low | F12: Low | G12: Low | H12: Low | I12: Low | J12: Low | K12: Med | L12: Med | M12: 0 | N12: Med | O12: Undesirable, consider engineer actions to mitigate risk | P12: 0 | Q12: 0
A13: 0 | B13: 2 | C13: Low | D13: Low | E13: Low | F13: Low | G13: Low | H13: Low | I13: Low | J13: Low | K13: Low | L13: Med | M13: 0 | N13: High | O13: Intolerable, engineering action required | P13: 0 | Q13: 0
A14: 0 | B14: 1 | C14: Low | D14: Low | E14: Low | F14: Low | G14: Low | H14: Low | I14: Low | J14: Low | K14: Low | L14: Low | M14: 0 | N14: 0 | O14: 0 | P14: 0 | Q14: 0
A15: 0 | B15: 0 | C15: 0 | D15: 0 | E15: 0 | F15: 0 | G15: 0 | H15: 0 | I15: 0 | J15: 0 | K15: 0 | L15: 0 | M15: 0 | N15: 0 | O15: 0 | P15: 0 | Q15: 0
A16: 0 | B16: Occurrence | C16: 0 | D16: 0 | E16: 0 | F16: 0 | G16: 0 | H16: Severity | I16: 0 | J16: 0 | K16: 0 | L16: 0 | M16: 0 | N16: 0 | O16: 0 | P16: 0 | Q16: 0
A17: 0 | B17: Rating | C17: Occurrence | D17: 0 | E17: Annual Failure Rate | F17: Return Period [years] | G17: 0 | H17: Rating | I17: Severity | J17: Human Safety | K17: 0 | L17: Environment | M17: 0 | N17: WEC Operation | O17: 0 | P17: Assets | Q17: 0
A18: 0 | B18: 1 | C18: Exceptionally unlikely to occur | D18: 0 | E18: 1e-05 | F18: 100000 | G18: 0 | H18: 1 | I18: Insignificant | J18: Negligible injury, effect on health (e.g. band aid) | K18: 0 | L18: Negligible pollution or no effect on environment | M18: 0 | N18: Negligible effect on performance | O18: 0 | P18: Negligible | Q18: 0
A19: 0 | B19: 2 | C19: 0 | D19: 0 | E19: 3.1622777e-05 | F19: 31600 | G19: 0 | H19: 2 | I19: 0 | J19: 0 | K19: 0 | L19: 0 | M19: 0 | N19: 0 | O19: 0 | P19: [1.5k USD] | Q19: 0
A20: 0 | B20: 3 | C20: Extremely unlikely to occur | D20: 0 | E20: 0.0001 | F20: 10000 | G20: 0 | H20: 3 | I20: Minor | J20: Minor injuries, health effects (e.g. stitches) | K20: 0 | L20: Minor pollution / slight effect on environment (min disruption on marine life) | M20: 0 | N20: Minor system degradation | O20: 0 | P20: Repairable in-situ, at next maintenance interval [5k USD] | Q20: 0
A21: 0 | B21: 4 | C21: 0 | D21: 0 | E21: 0.00031622777 | F21: 3160 | G21: 0 | H21: 4 | I21: 0 | J21: Moderate injuries and/or health effects (e.g. broken bone) | K21: 0 | L21: 0 | M21: 0 | N21: Moderate system degradation (e.g. loss of MoMo) | O21: 0 | P21: Repairable in-situ, outside maintenance interval (1 day) [15k USD] | Q21: 0
A22: 0 | B22: 5 | C22: Very unlikely to occur | D22: 0 | E22: 0.001 | F22: 1000 | G22: 0 | H22: 5 | I22: Major | J22: 0 | K22: 0 | L22: Limited levels of pollution, manageable / moderate effect on environment | M22: 0 | N22: 0 | O22: 0 | P22: Repairable in-situ, outside maintenance interval (1 week) [50k USD] | Q22: 0
A23: 0 | B23: 6 | C23: 0 | D23: 0 | E23: 0.0031622777 | F23: 316 | G23: 0 | H23: 6 | I23: 0 | J23: 0 | K23: 0 | L23: 0 | M23: 0 | N23: Major system degradation or loss of operation for 1 month | O23: 0 | P23: [150k USD] | Q23: 0
A24: 0 | B24: 7 | C24: Rarely expected to occur | D24: 0 | E24: 0.01 | F24: 100 | G24: 0 | H24: 7 | I24: Critical | J24: Hospitalization (with full recovery) | K24: 0 | L24: Moderate pollution (some clean-up costs) / Serious effect on environment | M24: 0 | N24: Major system degradation or loss of operation for 3 months | O24: 0 | P24: Dry dock required for repair [500k USD] | Q24: 0
A25: 0 | B25: 8 | C25: 0 | D25: 0 | E25: 0.031622777 | F25: 31.6 | G25: 0 | H25: 8 | I25: 0 | J25: 0 | K25: 0 | L25: 0 | M25: 0 | N25: Critical system degradation or loss of operation for 6 months | O25: 0 | P25: [1.5M USD] | Q25: 0
A26: 0 | B26: 9 | C26: One or more during 20 yr lifetime | D26: 0 | E26: 0.1 | F26: 10 | G26: 0 | H26: 9 | I26: Catastrophic | J26: Hospitalization (with lasting disabilities) | K26: 0 | L26: Major pollution (significant clean-up costs) / disastrous effects on the environment | M26: 0 | N26: Failure to generate power for remainder of project, complete failure | O26: 0 | P26: Loss of device [5M USD] | Q26: 0
A27: 0 | B27: 10 | C27: 0 | D27: 0 | E27: 0.31622777 | F27: 3.16 | G27: 0 | H27: 10 | I27: 0 | J27: A fatality | K27: 0 | L27: 0 | M27: 0 | N27: 0 | O27: 0 | P27: 0 | Q27: 0
